Workbook

Sheet flowssummary
A1: Category | B1: Type | C1: 1 | D1: 2 | E1: 3 | F1: 4 | G1: 5 | H1: 6 | I1: 7 | J1: 8 | K1: 9 | L1: 10 | M1: 11 | N1: 12
A2: Bank | B2: Product | C2: Opening balance | D2: Operation | E2: Closing balance | F2: {=SUMIFS(operations[[Amount]:[Amount]],operations[[Category]:[Category]],summary17[[#This Row],[Category]:[Category]],operations[[Month]:[Month]],summary17[[#Headers],[4]])} -> 0 | G2: {=SUMIFS(operations[[Amount]:[Amount]],operations[[Category]:[Category]],summary17[[#This Row],[Category]:[Category]],operations[[Month]:[Month]],summary17[[#Headers],[5]])} -> 0 | H2: {=SUMIFS(operations[[Amount]:[Amount]],operations[[Category]:[Category]],summary17[[#This Row],[Category]:[Category]],operations[[Month]:[Month]],summary17[[#Headers],[6]])} -> 0 | I2: {=SUMIFS(operations[[Amount]:[Amount]],operations[[Category]:[Category]],summary17[[#This Row],[Category]:[Category]],operations[[Month]:[Month]],summary17[[#Headers],[7]])} -> 0 | J2: {=SUMIFS(operations[[Amount]:[Amount]],operations[[Category]:[Category]],summary17[[#This Row],[Category]:[Category]],operations[[Month]:[Month]],summary17[[#Headers],[8]])} -> 0 | K2: {=SUMIFS(operations[[Amount]:[Amount]],operations[[Category]:[Category]],summary17[[#This Row],[Category]:[Category]],operations[[Month]:[Month]],summary17[[#Headers],[9]])} -> 0 | L2: {=SUMIFS(operations[[Amount]:[Amount]],operations[[Category]:[Category]],summary17[[#This Row],[Category]:[Category]],operations[[Month]:[Month]],summary17[[#Headers],[10]])} -> 0 | M2: {=SUMIFS(operations[[Amount]:[Amount]],operations[[Category]:[Category]],summary17[[#This Row],[Category]:[Category]],operations[[Month]:[Month]],summary17[[#Headers],[11]])} -> 0 | N2: {=SUMIFS(operations[[Amount]:[Amount]],operations[[Category]:[Category]],summary17[[#This Row],[Category]:[Category]],operations[[Month]:[Month]],summary17[[#Headers],[12]])} -> 0
A3: Millennium | B3: Account | C3: 100 | D3: -35 | E3: 65 | F3: {=SUMIFS(operations[[Amount]:[Amount]],operations[[Category]:[Category]],summary17[[#This Row],[Category]:[Category]],operations[[Month]:[Month]],summary17[[#Headers],[4]])} -> 0 | G3: {=SUMIFS(operations[[Amount]:[Amount]],operations[[Category]:[Category]],summary17[[#This Row],[Category]:[Category]],operations[[Month]:[Month]],summary17[[#Headers],[5]])} -> 0 | H3: {=SUMIFS(operations[[Amount]:[Amount]],operations[[Category]:[Category]],summary17[[#This Row],[Category]:[Category]],operations[[Month]:[Month]],summary17[[#Headers],[6]])} -> 0 | I3: {=SUMIFS(operations[[Amount]:[Amount]],operations[[Category]:[Category]],summary17[[#This Row],[Category]:[Category]],operations[[Month]:[Month]],summary17[[#Headers],[7]])} -> 0 | J3: {=SUMIFS(operations[[Amount]:[Amount]],operations[[Category]:[Category]],summary17[[#This Row],[Category]:[Category]],operations[[Month]:[Month]],summary17[[#Headers],[8]])} -> 0 | K3: {=SUMIFS(operations[[Amount]:[Amount]],operations[[Category]:[Category]],summary17[[#This Row],[Category]:[Category]],operations[[Month]:[Month]],summary17[[#Headers],[9]])} -> 0 | L3: {=SUMIFS(operations[[Amount]:[Amount]],operations[[Category]:[Category]],summary17[[#This Row],[Category]:[Category]],operations[[Month]:[Month]],summary17[[#Headers],[10]])} -> 0 | M3: {=SUMIFS(operations[[Amount]:[Amount]],operations[[Category]:[Category]],summary17[[#This Row],[Category]:[Category]],operations[[Month]:[Month]],summary17[[#Headers],[11]])} -> 0 | N3: {=SUMIFS(operations[[Amount]:[Amount]],operations[[Category]:[Category]],summary17[[#This Row],[Category]:[Category]],operations[[Month]:[Month]],summary17[[#Headers],[12]])} -> 0
A4: Millennium | B4: Savings account | C4: 10.5 | D4: 255.5 | E4: 266 | F4: {=SUMIFS(operations[[Amount]:[Amount]],operations[[Category]:[Category]],summary17[[#This Row],[Category]:[Category]],operations[[Month]:[Month]],summary17[[#Headers],[4]])} -> 0 | G4: {=SUMIFS(operations[[Amount]:[Amount]],operations[[Category]:[Category]],summary17[[#This Row],[Category]:[Category]],operations[[Month]:[Month]],summary17[[#Headers],[5]])} -> 0 | H4: {=SUMIFS(operations[[Amount]:[Amount]],operations[[Category]:[Category]],summary17[[#This Row],[Category]:[Category]],operations[[Month]:[Month]],summary17[[#Headers],[6]])} -> 0 | I4: {=SUMIFS(operations[[Amount]:[Amount]],operations[[Category]:[Category]],summary17[[#This Row],[Category]:[Category]],operations[[Month]:[Month]],summary17[[#Headers],[7]])} -> 0 | J4: {=SUMIFS(operations[[Amount]:[Amount]],operations[[Category]:[Category]],summary17[[#This Row],[Category]:[Category]],operations[[Month]:[Month]],summary17[[#Headers],[8]])} -> 0 | K4: {=SUMIFS(operations[[Amount]:[Amount]],operations[[Category]:[Category]],summary17[[#This Row],[Category]:[Category]],operations[[Month]:[Month]],summary17[[#Headers],[9]])} -> 0 | L4: {=SUMIFS(operations[[Amount]:[Amount]],operations[[Category]:[Category]],summary17[[#This Row],[Category]:[Category]],operations[[Month]:[Month]],summary17[[#Headers],[10]])} -> 0 | M4: {=SUMIFS(operations[[Amount]:[Amount]],operations[[Category]:[Category]],summary17[[#This Row],[Category]:[Category]],operations[[Month]:[Month]],summary17[[#Headers],[11]])} -> 0 | N4: {=SUMIFS(operations[[Amount]:[Amount]],operations[[Category]:[Category]],summary17[[#This Row],[Category]:[Category]],operations[[Month]:[Month]],summary17[[#Headers],[12]])} -> 0
A5: Santander | B5: Account | C5: 600 | D5: 1100 | E5: 1700 | F5: {=SUMIFS(operations[[Amount]:[Amount]],operations[[Category]:[Category]],summary17[[#This Row],[Category]:[Category]],operations[[Month]:[Month]],summary17[[#Headers],[4]])} -> 0 | G5: {=SUMIFS(operations[[Amount]:[Amount]],operations[[Category]:[Category]],summary17[[#This Row],[Category]:[Category]],operations[[Month]:[Month]],summary17[[#Headers],[5]])} -> 0 | H5: {=SUMIFS(operations[[Amount]:[Amount]],operations[[Category]:[Category]],summary17[[#This Row],[Category]:[Category]],operations[[Month]:[Month]],summary17[[#Headers],[6]])} -> 0 | I5: {=SUMIFS(operations[[Amount]:[Amount]],operations[[Category]:[Category]],summary17[[#This Row],[Category]:[Category]],operations[[Month]:[Month]],summary17[[#Headers],[7]])} -> 0 | J5: {=SUMIFS(operations[[Amount]:[Amount]],operations[[Category]:[Category]],summary17[[#This Row],[Category]:[Category]],operations[[Month]:[Month]],summary17[[#Headers],[8]])} -> 0 | K5: {=SUMIFS(operations[[Amount]:[Amount]],operations[[Category]:[Category]],summary17[[#This Row],[Category]:[Category]],operations[[Month]:[Month]],summary17[[#Headers],[9]])} -> 0 | L5: {=SUMIFS(operations[[Amount]:[Amount]],operations[[Category]:[Category]],summary17[[#This Row],[Category]:[Category]],operations[[Month]:[Month]],summary17[[#Headers],[10]])} -> 0 | M5: {=SUMIFS(operations[[Amount]:[Amount]],operations[[Category]:[Category]],summary17[[#This Row],[Category]:[Category]],operations[[Month]:[Month]],summary17[[#Headers],[11]])} -> 0 | N5: {=SUMIFS(operations[[Amount]:[Amount]],operations[[Category]:[Category]],summary17[[#This Row],[Category]:[Category]],operations[[Month]:[Month]],summary17[[#Headers],[12]])} -> 0
A6: Santander | B6: Credit card | C6: 0 | D6: -175 | E6: -175 | F6: {=SUMIFS(operations[[Amount]:[Amount]],operations[[Category]:[Category]],summary17[[#This Row],[Category]:[Category]],operations[[Month]:[Month]],summary17[[#Headers],[4]])} -> 0 | G6: {=SUMIFS(operations[[Amount]:[Amount]],operations[[Category]:[Category]],summary17[[#This Row],[Category]:[Category]],operations[[Month]:[Month]],summary17[[#Headers],[5]])} -> 0 | H6: {=SUMIFS(operations[[Amount]:[Amount]],operations[[Category]:[Category]],summary17[[#This Row],[Category]:[Category]],operations[[Month]:[Month]],summary17[[#Headers],[6]])} -> 0 | I6: {=SUMIFS(operations[[Amount]:[Amount]],operations[[Category]:[Category]],summary17[[#This Row],[Category]:[Category]],operations[[Month]:[Month]],summary17[[#Headers],[7]])} -> 0 | J6: {=SUMIFS(operations[[Amount]:[Amount]],operations[[Category]:[Category]],summary17[[#This Row],[Category]:[Category]],operations[[Month]:[Month]],summary17[[#Headers],[8]])} -> 0 | K6: {=SUMIFS(operations[[Amount]:[Amount]],operations[[Category]:[Category]],summary17[[#This Row],[Category]:[Category]],operations[[Month]:[Month]],summary17[[#Headers],[9]])} -> 0 | L6: {=SUMIFS(operations[[Amount]:[Amount]],operations[[Category]:[Category]],summary17[[#This Row],[Category]:[Category]],operations[[Month]:[Month]],summary17[[#Headers],[10]])} -> 0 | M6: {=SUMIFS(operations[[Amount]:[Amount]],operations[[Category]:[Category]],summary17[[#This Row],[Category]:[Category]],operations[[Month]:[Month]],summary17[[#Headers],[11]])} -> 0 | N6: {=SUMIFS(operations[[Amount]:[Amount]],operations[[Category]:[Category]],summary17[[#This Row],[Category]:[Category]],operations[[Month]:[Month]],summary17[[#Headers],[12]])} -> 0
A7: Santander | B7: Fixed-term deposit | C7: 2000 | D7: -400 | E7: 1600 | F7: {=SUMIFS(operations[[Amount]:[Amount]],operations[[Category]:[Category]],summary17[[#This Row],[Category]:[Category]],operations[[Month]:[Month]],summary17[[#Headers],[4]])} -> 0 | G7: {=SUMIFS(operations[[Amount]:[Amount]],operations[[Category]:[Category]],summary17[[#This Row],[Category]:[Category]],operations[[Month]:[Month]],summary17[[#Headers],[5]])} -> 0 | H7: {=SUMIFS(operations[[Amount]:[Amount]],operations[[Category]:[Category]],summary17[[#This Row],[Category]:[Category]],operations[[Month]:[Month]],summary17[[#Headers],[6]])} -> 0 | I7: {=SUMIFS(operations[[Amount]:[Amount]],operations[[Category]:[Category]],summary17[[#This Row],[Category]:[Category]],operations[[Month]:[Month]],summary17[[#Headers],[7]])} -> 0 | J7: {=SUMIFS(operations[[Amount]:[Amount]],operations[[Category]:[Category]],summary17[[#This Row],[Category]:[Category]],operations[[Month]:[Month]],summary17[[#Headers],[8]])} -> 0 | K7: {=SUMIFS(operations[[Amount]:[Amount]],operations[[Category]:[Category]],summary17[[#This Row],[Category]:[Category]],operations[[Month]:[Month]],summary17[[#Headers],[9]])} -> 0 | L7: {=SUMIFS(operations[[Amount]:[Amount]],operations[[Category]:[Category]],summary17[[#This Row],[Category]:[Category]],operations[[Month]:[Month]],summary17[[#Headers],[10]])} -> 0 | M7: {=SUMIFS(operations[[Amount]:[Amount]],operations[[Category]:[Category]],summary17[[#This Row],[Category]:[Category]],operations[[Month]:[Month]],summary17[[#Headers],[11]])} -> 0 | N7: {=SUMIFS(operations[[Amount]:[Amount]],operations[[Category]:[Category]],summary17[[#This Row],[Category]:[Category]],operations[[Month]:[Month]],summary17[[#Headers],[12]])} -> 0
A8: Wallet | B8: Gift card | C8: 200 | D8: -50 | E8: 150 | F8: {=SUMIFS(operations[[Amount]:[Amount]],operations[[Category]:[Category]],summary17[[#This Row],[Category]:[Category]],operations[[Month]:[Month]],summary17[[#Headers],[4]])} -> 0 | G8: {=SUMIFS(operations[[Amount]:[Amount]],operations[[Category]:[Category]],summary17[[#This Row],[Category]:[Category]],operations[[Month]:[Month]],summary17[[#Headers],[5]])} -> 0 | H8: {=SUMIFS(operations[[Amount]:[Amount]],operations[[Category]:[Category]],summary17[[#This Row],[Category]:[Category]],operations[[Month]:[Month]],summary17[[#Headers],[6]])} -> 0 | I8: {=SUMIFS(operations[[Amount]:[Amount]],operations[[Category]:[Category]],summary17[[#This Row],[Category]:[Category]],operations[[Month]:[Month]],summary17[[#Headers],[7]])} -> 0 | J8: {=SUMIFS(operations[[Amount]:[Amount]],operations[[Category]:[Category]],summary17[[#This Row],[Category]:[Category]],operations[[Month]:[Month]],summary17[[#Headers],[8]])} -> 0 | K8: {=SUMIFS(operations[[Amount]:[Amount]],operations[[Category]:[Category]],summary17[[#This Row],[Category]:[Category]],operations[[Month]:[Month]],summary17[[#Headers],[9]])} -> 0 | L8: {=SUMIFS(operations[[Amount]:[Amount]],operations[[Category]:[Category]],summary17[[#This Row],[Category]:[Category]],operations[[Month]:[Month]],summary17[[#Headers],[10]])} -> 0 | M8: {=SUMIFS(operations[[Amount]:[Amount]],operations[[Category]:[Category]],summary17[[#This Row],[Category]:[Category]],operations[[Month]:[Month]],summary17[[#Headers],[11]])} -> 0 | N8: {=SUMIFS(operations[[Amount]:[Amount]],operations[[Category]:[Category]],summary17[[#This Row],[Category]:[Category]],operations[[Month]:[Month]],summary17[[#Headers],[12]])} -> 0
A9: Wallet | B9: Money | C9: 30 | D9: 150 | E9: 180 | F9: {=SUMIFS(operations[[Amount]:[Amount]],operations[[Category]:[Category]],summary17[[#This Row],[Category]:[Category]],operations[[Month]:[Month]],summary17[[#Headers],[4]])} -> 0 | G9: {=SUMIFS(operations[[Amount]:[Amount]],operations[[Category]:[Category]],summary17[[#This Row],[Category]:[Category]],operations[[Month]:[Month]],summary17[[#Headers],[5]])} -> 0 | H9: {=SUMIFS(operations[[Amount]:[Amount]],operations[[Category]:[Category]],summary17[[#This Row],[Category]:[Category]],operations[[Month]:[Month]],summary17[[#Headers],[6]])} -> 0 | I9: {=SUMIFS(operations[[Amount]:[Amount]],operations[[Category]:[Category]],summary17[[#This Row],[Category]:[Category]],operations[[Month]:[Month]],summary17[[#Headers],[7]])} -> 0 | J9: {=SUMIFS(operations[[Amount]:[Amount]],operations[[Category]:[Category]],summary17[[#This Row],[Category]:[Category]],operations[[Month]:[Month]],summary17[[#Headers],[8]])} -> 0 | K9: {=SUMIFS(operations[[Amount]:[Amount]],operations[[Category]:[Category]],summary17[[#This Row],[Category]:[Category]],operations[[Month]:[Month]],summary17[[#Headers],[9]])} -> 0 | L9: {=SUMIFS(operations[[Amount]:[Amount]],operations[[Category]:[Category]],summary17[[#This Row],[Category]:[Category]],operations[[Month]:[Month]],summary17[[#Headers],[10]])} -> 0 | M9: {=SUMIFS(operations[[Amount]:[Amount]],operations[[Category]:[Category]],summary17[[#This Row],[Category]:[Category]],operations[[Month]:[Month]],summary17[[#Headers],[11]])} -> 0 | N9: {=SUMIFS(operations[[Amount]:[Amount]],operations[[Category]:[Category]],summary17[[#This Row],[Category]:[Category]],operations[[Month]:[Month]],summary17[[#Headers],[12]])} -> 0
A10: Total | C10: 2940.5 | D10: 845.5 | E10: 3786 | F10: {=SUMIFS(operations[[Amount]:[Amount]],operations[[Category]:[Category]],summary17[[#This Row],[Category]:[Category]],operations[[Month]:[Month]],summary17[[#Headers],[4]])} -> 0 | G10: {=SUMIFS(operations[[Amount]:[Amount]],operations[[Category]:[Category]],summary17[[#This Row],[Category]:[Category]],operations[[Month]:[Month]],summary17[[#Headers],[5]])} -> 0 | H10: {=SUMIFS(operations[[Amount]:[Amount]],operations[[Category]:[Category]],summary17[[#This Row],[Category]:[Category]],operations[[Month]:[Month]],summary17[[#Headers],[6]])} -> 0 | I10: {=SUMIFS(operations[[Amount]:[Amount]],operations[[Category]:[Category]],summary17[[#This Row],[Category]:[Category]],operations[[Month]:[Month]],summary17[[#Headers],[7]])} -> 0 | J10: {=SUMIFS(operations[[Amount]:[Amount]],operations[[Category]:[Category]],summary17[[#This Row],[Category]:[Category]],operations[[Month]:[Month]],summary17[[#Headers],[8]])} -> 0 | K10: {=SUMIFS(operations[[Amount]:[Amount]],operations[[Category]:[Category]],summary17[[#This Row],[Category]:[Category]],operations[[Month]:[Month]],summary17[[#Headers],[9]])} -> 0 | L10: {=SUMIFS(operations[[Amount]:[Amount]],operations[[Category]:[Category]],summary17[[#This Row],[Category]:[Category]],operations[[Month]:[Month]],summary17[[#Headers],[10]])} -> 0 | M10: {=SUMIFS(operations[[Amount]:[Amount]],operations[[Category]:[Category]],summary17[[#This Row],[Category]:[Category]],operations[[Month]:[Month]],summary17[[#Headers],[11]])} -> 0 | N10: {=SUMIFS(operations[[Amount]:[Amount]],operations[[Category]:[Category]],summary17[[#This Row],[Category]:[Category]],operations[[Month]:[Month]],summary17[[#Headers],[12]])} -> 0
A11: Allowance | B11: Income | C11: {=SUMIFS(operations[[Amount]:[Amount]],operations[[Category]:[Category]],summary17[[#This Row],[Category]:[Category]],operations[[Month]:[Month]],summary17[[#Headers],[1]])} -> 250 | D11: {=SUMIFS(operations[[Amount]:[Amount]],operations[[Category]:[Category]],summary17[[#This Row],[Category]:[Category]],operations[[Month]:[Month]],summary17[[#Headers],[2]])} -> 0 | E11: {=SUMIFS(operations[[Amount]:[Amount]],operations[[Category]:[Category]],summary17[[#This Row],[Category]:[Category]],operations[[Month]:[Month]],summary17[[#Headers],[3]])} -> 0 | F11: {=SUMIFS(operations[[Amount]:[Amount]],operations[[Category]:[Category]],summary17[[#This Row],[Category]:[Category]],operations[[Month]:[Month]],summary17[[#Headers],[4]])} -> 0 | G11: {=SUMIFS(operations[[Amount]:[Amount]],operations[[Category]:[Category]],summary17[[#This Row],[Category]:[Category]],operations[[Month]:[Month]],summary17[[#Headers],[5]])} -> 0 | H11: {=SUMIFS(operations[[Amount]:[Amount]],operations[[Category]:[Category]],summary17[[#This Row],[Category]:[Category]],operations[[Month]:[Month]],summary17[[#Headers],[6]])} -> 400 | I11: {=SUMIFS(operations[[Amount]:[Amount]],operations[[Category]:[Category]],summary17[[#This Row],[Category]:[Category]],operations[[Month]:[Month]],summary17[[#Headers],[7]])} -> 0 | J11: {=SUMIFS(operations[[Amount]:[Amount]],operations[[Category]:[Category]],summary17[[#This Row],[Category]:[Category]],operations[[Month]:[Month]],summary17[[#Headers],[8]])} -> 0 | K11: {=SUMIFS(operations[[Amount]:[Amount]],operations[[Category]:[Category]],summary17[[#This Row],[Category]:[Category]],operations[[Month]:[Month]],summary17[[#Headers],[9]])} -> 0 | L11: {=SUMIFS(operations[[Amount]:[Amount]],operations[[Category]:[Category]],summary17[[#This Row],[Category]:[Category]],operations[[Month]:[Month]],summary17[[#Headers],[10]])} -> 0 | M11: {=SUMIFS(operations[[Amount]:[Amount]],operations[[Category]:[Category]],summary17[[#This Row],[Category]:[Category]],operations[[Month]:[Month]],summary17[[#Headers],[11]])} -> 0 | N11: {=SUMIFS(operations[[Amount]:[Amount]],operations[[Category]:[Category]],summary17[[#This Row],[Category]:[Category]],operations[[Month]:[Month]],summary17[[#Headers],[12]])} -> 0
A12: Financial | B12: Income | C12: {=SUMIFS(operations[[Amount]:[Amount]],operations[[Category]:[Category]],summary17[[#This Row],[Category]:[Category]],operations[[Month]:[Month]],summary17[[#Headers],[1]])} -> 105.5 | D12: {=SUMIFS(operations[[Amount]:[Amount]],operations[[Category]:[Category]],summary17[[#This Row],[Category]:[Category]],operations[[Month]:[Month]],summary17[[#Headers],[2]])} -> 115 | E12: {=SUMIFS(operations[[Amount]:[Amount]],operations[[Category]:[Category]],summary17[[#This Row],[Category]:[Category]],operations[[Month]:[Month]],summary17[[#Headers],[3]])} -> 150 | F12: {=SUMIFS(operations[[Amount]:[Amount]],operations[[Category]:[Category]],summary17[[#This Row],[Category]:[Category]],operations[[Month]:[Month]],summary17[[#Headers],[4]])} -> 150 | G12: {=SUMIFS(operations[[Amount]:[Amount]],operations[[Category]:[Category]],summary17[[#This Row],[Category]:[Category]],operations[[Month]:[Month]],summary17[[#Headers],[5]])} -> 0 | H12: {=SUMIFS(operations[[Amount]:[Amount]],operations[[Category]:[Category]],summary17[[#This Row],[Category]:[Category]],operations[[Month]:[Month]],summary17[[#Headers],[6]])} -> 0 | I12: {=SUMIFS(operations[[Amount]:[Amount]],operations[[Category]:[Category]],summary17[[#This Row],[Category]:[Category]],operations[[Month]:[Month]],summary17[[#Headers],[7]])} -> 120 | J12: {=SUMIFS(operations[[Amount]:[Amount]],operations[[Category]:[Category]],summary17[[#This Row],[Category]:[Category]],operations[[Month]:[Month]],summary17[[#Headers],[8]])} -> 0 | K12: {=SUMIFS(operations[[Amount]:[Amount]],operations[[Category]:[Category]],summary17[[#This Row],[Category]:[Category]],operations[[Month]:[Month]],summary17[[#Headers],[9]])} -> 0 | L12: {=SUMIFS(operations[[Amount]:[Amount]],operations[[Category]:[Category]],summary17[[#This Row],[Category]:[Category]],operations[[Month]:[Month]],summary17[[#Headers],[10]])} -> 0 | M12: {=SUMIFS(operations[[Amount]:[Amount]],operations[[Category]:[Category]],summary17[[#This Row],[Category]:[Category]],operations[[Month]:[Month]],summary17[[#Headers],[11]])} -> 0 | N12: {=SUMIFS(operations[[Amount]:[Amount]],operations[[Category]:[Category]],summary17[[#This Row],[Category]:[Category]],operations[[Month]:[Month]],summary17[[#Headers],[12]])} -> 0
A13: Gift | B13: Income | C13: {=SUMIFS(operations[[Amount]:[Amount]],operations[[Category]:[Category]],summary17[[#This Row],[Category]:[Category]],operations[[Month]:[Month]],summary17[[#Headers],[1]])} -> 0 | D13: {=SUMIFS(operations[[Amount]:[Amount]],operations[[Category]:[Category]],summary17[[#This Row],[Category]:[Category]],operations[[Month]:[Month]],summary17[[#Headers],[2]])} -> 0 | E13: {=SUMIFS(operations[[Amount]:[Amount]],operations[[Category]:[Category]],summary17[[#This Row],[Category]:[Category]],operations[[Month]:[Month]],summary17[[#Headers],[3]])} -> 5 | F13: {=SUMIFS(operations[[Amount]:[Amount]],operations[[Category]:[Category]],summary17[[#This Row],[Category]:[Category]],operations[[Month]:[Month]],summary17[[#Headers],[4]])} -> 50 | G13: {=SUMIFS(operations[[Amount]:[Amount]],operations[[Category]:[Category]],summary17[[#This Row],[Category]:[Category]],operations[[Month]:[Month]],summary17[[#Headers],[5]])} -> 0 | H13: {=SUMIFS(operations[[Amount]:[Amount]],operations[[Category]:[Category]],summary17[[#This Row],[Category]:[Category]],operations[[Month]:[Month]],summary17[[#Headers],[6]])} -> 0 | I13: {=SUMIFS(operations[[Amount]:[Amount]],operations[[Category]:[Category]],summary17[[#This Row],[Category]:[Category]],operations[[Month]:[Month]],summary17[[#Headers],[7]])} -> 800 | J13: {=SUMIFS(operations[[Amount]:[Amount]],operations[[Category]:[Category]],summary17[[#This Row],[Category]:[Category]],operations[[Month]:[Month]],summary17[[#Headers],[8]])} -> 400 | K13: {=SUMIFS(operations[[Amount]:[Amount]],operations[[Category]:[Category]],summary17[[#This Row],[Category]:[Category]],operations[[Month]:[Month]],summary17[[#Headers],[9]])} -> 0 | L13: {=SUMIFS(operations[[Amount]:[Amount]],operations[[Category]:[Category]],summary17[[#This Row],[Category]:[Category]],operations[[Month]:[Month]],summary17[[#Headers],[10]])} -> 0 | M13: {=SUMIFS(operations[[Amount]:[Amount]],operations[[Category]:[Category]],summary17[[#This Row],[Category]:[Category]],operations[[Month]:[Month]],summary17[[#Headers],[11]])} -> 400 | N13: {=SUMIFS(operations[[Amount]:[Amount]],operations[[Category]:[Category]],summary17[[#This Row],[Category]:[Category]],operations[[Month]:[Month]],summary17[[#Headers],[12]])} -> 2000
A14: Other incoms | B14: Income | C14: {=SUMIFS(operations[[Amount]:[Amount]],operations[[Category]:[Category]],summary17[[#This Row],[Category]:[Category]],operations[[Month]:[Month]],summary17[[#Headers],[1]])} -> 800 | D14: {=SUMIFS(operations[[Amount]:[Amount]],operations[[Category]:[Category]],summary17[[#This Row],[Category]:[Category]],operations[[Month]:[Month]],summary17[[#Headers],[2]])} -> 1950 | E14: {=SUMIFS(operations[[Amount]:[Amount]],operations[[Category]:[Category]],summary17[[#This Row],[Category]:[Category]],operations[[Month]:[Month]],summary17[[#Headers],[3]])} -> 0 | F14: {=SUMIFS(operations[[Amount]:[Amount]],operations[[Category]:[Category]],summary17[[#This Row],[Category]:[Category]],operations[[Month]:[Month]],summary17[[#Headers],[4]])} -> 0 | G14: {=SUMIFS(operations[[Amount]:[Amount]],operations[[Category]:[Category]],summary17[[#This Row],[Category]:[Category]],operations[[Month]:[Month]],summary17[[#Headers],[5]])} -> 0 | H14: {=SUMIFS(operations[[Amount]:[Amount]],operations[[Category]:[Category]],summary17[[#This Row],[Category]:[Category]],operations[[Month]:[Month]],summary17[[#Headers],[6]])} -> 0 | I14: {=SUMIFS(operations[[Amount]:[Amount]],operations[[Category]:[Category]],summary17[[#This Row],[Category]:[Category]],operations[[Month]:[Month]],summary17[[#Headers],[7]])} -> 0 | J14: {=SUMIFS(operations[[Amount]:[Amount]],operations[[Category]:[Category]],summary17[[#This Row],[Category]:[Category]],operations[[Month]:[Month]],summary17[[#Headers],[8]])} -> 0 | K14: {=SUMIFS(operations[[Amount]:[Amount]],operations[[Category]:[Category]],summary17[[#This Row],[Category]:[Category]],operations[[Month]:[Month]],summary17[[#Headers],[9]])} -> 0 | L14: {=SUMIFS(operations[[Amount]:[Amount]],operations[[Category]:[Category]],summary17[[#This Row],[Category]:[Category]],operations[[Month]:[Month]],summary17[[#Headers],[10]])} -> 0 | M14: {=SUMIFS(operations[[Amount]:[Amount]],operations[[Category]:[Category]],summary17[[#This Row],[Category]:[Category]],operations[[Month]:[Month]],summary17[[#Headers],[11]])} -> 0 | N14: =SUBTOTAL(109,summary17[12]) -> -405
A15: Salary | B15: Income | C15: {=SUMIFS(operations[[Amount]:[Amount]],operations[[Category]:[Category]],summary17[[#This Row],[Category]:[Category]],operations[[Month]:[Month]],summary17[[#Headers],[1]])} -> 4500 | D15: {=SUMIFS(operations[[Amount]:[Amount]],operations[[Category]:[Category]],summary17[[#This Row],[Category]:[Category]],operations[[Month]:[Month]],summary17[[#Headers],[2]])} -> 4500 | E15: {=SUMIFS(operations[[Amount]:[Amount]],operations[[Category]:[Category]],summary17[[#This Row],[Category]:[Category]],operations[[Month]:[Month]],summary17[[#Headers],[3]])} -> 4500 | F15: {=SUMIFS(operations[[Amount]:[Amount]],operations[[Category]:[Category]],summary17[[#This Row],[Category]:[Category]],operations[[Month]:[Month]],summary17[[#Headers],[4]])} -> 4500 | G15: {=SUMIFS(operations[[Amount]:[Amount]],operations[[Category]:[Category]],summary17[[#This Row],[Category]:[Category]],operations[[Month]:[Month]],summary17[[#Headers],[5]])} -> 4500 | H15: {=SUMIFS(operations[[Amount]:[Amount]],operations[[Category]:[Category]],summary17[[#This Row],[Category]:[Category]],operations[[Month]:[Month]],summary17[[#Headers],[6]])} -> 4500 | I15: {=SUMIFS(operations[[Amount]:[Amount]],operations[[Category]:[Category]],summary17[[#This Row],[Category]:[Category]],operations[[Month]:[Month]],summary17[[#Headers],[7]])} -> 4500 | J15: {=SUMIFS(operations[[Amount]:[Amount]],operations[[Category]:[Category]],summary17[[#This Row],[Category]:[Category]],operations[[Month]:[Month]],summary17[[#Headers],[8]])} -> 4500 | K15: {=SUMIFS(operations[[Amount]:[Amount]],operations[[Category]:[Category]],summary17[[#This Row],[Category]:[Category]],operations[[Month]:[Month]],summary17[[#Headers],[9]])} -> 4500 | L15: {=SUMIFS(operations[[Amount]:[Amount]],operations[[Category]:[Category]],summary17[[#This Row],[Category]:[Category]],operations[[Month]:[Month]],summary17[[#Headers],[10]])} -> 4500 | M15: {=SUMIFS(operations[[Amount]:[Amount]],operations[[Category]:[Category]],summary17[[#This Row],[Category]:[Category]],operations[[Month]:[Month]],summary17[[#Headers],[11]])} -> 4500 | N15: =SUBTOTAL(109,summary17[12]) -> -405
A16: Scholarship | B16: Income | C16: {=SUMIFS(operations[[Amount]:[Amount]],operations[[Category]:[Category]],summary17[[#This Row],[Category]:[Category]],operations[[Month]:[Month]],summary17[[#Headers],[1]])} -> 0 | D16: {=SUMIFS(operations[[Amount]:[Amount]],operations[[Category]:[Category]],summary17[[#This Row],[Category]:[Category]],operations[[Month]:[Month]],summary17[[#Headers],[2]])} -> 0 | E16: {=SUMIFS(operations[[Amount]:[Amount]],operations[[Category]:[Category]],summary17[[#This Row],[Category]:[Category]],operations[[Month]:[Month]],summary17[[#Headers],[3]])} -> 0 | F16: {=SUMIFS(operations[[Amount]:[Amount]],operations[[Category]:[Category]],summary17[[#This Row],[Category]:[Category]],operations[[Month]:[Month]],summary17[[#Headers],[4]])} -> 0 | G16: {=SUMIFS(operations[[Amount]:[Amount]],operations[[Category]:[Category]],summary17[[#This Row],[Category]:[Category]],operations[[Month]:[Month]],summary17[[#Headers],[5]])} -> 0 | H16: {=SUMIFS(operations[[Amount]:[Amount]],operations[[Category]:[Category]],summary17[[#This Row],[Category]:[Category]],operations[[Month]:[Month]],summary17[[#Headers],[6]])} -> 0 | I16: {=SUMIFS(operations[[Amount]:[Amount]],operations[[Category]:[Category]],summary17[[#This Row],[Category]:[Category]],operations[[Month]:[Month]],summary17[[#Headers],[7]])} -> 500 | J16: {=SUMIFS(operations[[Amount]:[Amount]],operations[[Category]:[Category]],summary17[[#This Row],[Category]:[Category]],operations[[Month]:[Month]],summary17[[#Headers],[8]])} -> 500 | K16: {=SUMIFS(operations[[Amount]:[Amount]],operations[[Category]:[Category]],summary17[[#This Row],[Category]:[Category]],operations[[Month]:[Month]],summary17[[#Headers],[9]])} -> 0 | L16: {=SUMIFS(operations[[Amount]:[Amount]],operations[[Category]:[Category]],summary17[[#This Row],[Category]:[Category]],operations[[Month]:[Month]],summary17[[#Headers],[10]])} -> 0 | M16: {=SUMIFS(operations[[Amount]:[Amount]],operations[[Category]:[Category]],summary17[[#This Row],[Category]:[Category]],operations[[Month]:[Month]],summary17[[#Headers],[11]])} -> 0 | N16: =SUBTOTAL(109,summary17[12]) -> -405
A17: Transfer | B17: Transfer | C17: {=SUMIFS(operations[[Amount]:[Amount]],operations[[Category]:[Category]],summary17[[#This Row],[Category]:[Category]],operations[[Month]:[Month]],summary17[[#Headers],[1]])} -> 0 | D17: {=SUMIFS(operations[[Amount]:[Amount]],operations[[Category]:[Category]],summary17[[#This Row],[Category]:[Category]],operations[[Month]:[Month]],summary17[[#Headers],[2]])} -> 0 | E17: {=SUMIFS(operations[[Amount]:[Amount]],operations[[Category]:[Category]],summary17[[#This Row],[Category]:[Category]],operations[[Month]:[Month]],summary17[[#Headers],[3]])} -> 0 | F17: {=SUMIFS(operations[[Amount]:[Amount]],operations[[Category]:[Category]],summary17[[#This Row],[Category]:[Category]],operations[[Month]:[Month]],summary17[[#Headers],[4]])} -> 0 | G17: {=SUMIFS(operations[[Amount]:[Amount]],operations[[Category]:[Category]],summary17[[#This Row],[Category]:[Category]],operations[[Month]:[Month]],summary17[[#Headers],[5]])} -> 0 | H17: {=SUMIFS(operations[[Amount]:[Amount]],operations[[Category]:[Category]],summary17[[#This Row],[Category]:[Category]],operations[[Month]:[Month]],summary17[[#Headers],[6]])} -> 0 | I17: {=SUMIFS(operations[[Amount]:[Amount]],operations[[Category]:[Category]],summary17[[#This Row],[Category]:[Category]],operations[[Month]:[Month]],summary17[[#Headers],[7]])} -> 0 | J17: {=SUMIFS(operations[[Amount]:[Amount]],operations[[Category]:[Category]],summary17[[#This Row],[Category]:[Category]],operations[[Month]:[Month]],summary17[[#Headers],[8]])} -> -1020 | K17: {=SUMIFS(operations[[Amount]:[Amount]],operations[[Category]:[Category]],summary17[[#This Row],[Category]:[Category]],operations[[Month]:[Month]],summary17[[#Headers],[9]])} -> 0 | L17: {=SUMIFS(operations[[Amount]:[Amount]],operations[[Category]:[Category]],summary17[[#This Row],[Category]:[Category]],operations[[Month]:[Month]],summary17[[#Headers],[10]])} -> 0 | M17: {=SUMIFS(operations[[Amount]:[Amount]],operations[[Category]:[Category]],summary17[[#This Row],[Category]:[Category]],operations[[Month]:[Month]],summary17[[#Headers],[11]])} -> 0 | N17: =SUBTOTAL(109,summary17[12]) -> -405
A18: Total | C18: =SUBTOTAL(109,summary17[1]) -> 11536.5 | D18: =SUBTOTAL(109,summary17[2]) -> 8256 | E18: =SUBTOTAL(109,summary17[3]) -> 12227 | F18: =SUBTOTAL(109,summary17[4]) -> 4700 | G18: =SUBTOTAL(109,summary17[5]) -> 4500 | H18: =SUBTOTAL(109,summary17[6]) -> 4900 | I18: =SUBTOTAL(109,summary17[7]) -> 5920 | J18: =SUBTOTAL(109,summary17[8]) -> 4380 | K18: =SUBTOTAL(109,summary17[9]) -> 4500 | L18: =SUBTOTAL(109,summary17[10]) -> 4500 | M18: =SUBTOTAL(109,summary17[11]) -> 4900 | N18: =SUBTOTAL(109,summary17[12]) -> -405

Sheet 12
A1: Bank | B1: Product | C1: Opening balance | D1: Operation | E1: Closing balance | G1: Category | H1: Total | J1: Category | K1: Total | N1: Type
A2: Millennium | B2: Account | C2: {=INDIRECT("raport_"&$B$12-1&"[@[Closing balance ]]")} -> #REF! | D2: =SUMIFS(operations[Amount],operations[Bank],raports_12[[#This Row],[Bank]],operations[Product],raports_12[[#This Row],[Product]],operations[Month],$B$12) -> 0 | E2: =raports_12[[#This Row],[Opening balance]]+raports_12[[#This Row],[Operation]] -> #REF! | G2: Accomodation | H2: =SUMIFS(operations[Amount],operations[Category],Expenses12[[#This Row],[Category]],operations[Month],'1'!$B$12) -> -2000 | J2: Other expences | N2: Expense
A3: Millennium | B3: Savings account | C3: 10.5 | D3: =SUMIFS(operations[Amount],operations[Bank],raports_12[[#This Row],[Bank]],operations[Product],raports_12[[#This Row],[Product]],operations[Month],$B$12) -> 0 | E3: =raports_12[[#This Row],[Opening balance]]+raports_12[[#This Row],[Operation]] -> 10.5 | G3: Clothing | H3: =SUMIFS(operations[Amount],operations[Category],Expenses12[[#This Row],[Category]],operations[Month],'1'!$B$12) -> -80 | J3: Studies | K3: =SUMIFS(operations[Amount],operations[Category],Table916283236404448525660[[#This Row],[Category]],operations[Month],'1'!$B$12) -> -100 | N3: Expense
A4: Santander | B4: Account | C4: 600 | D4: =SUMIFS(operations[Amount],operations[Bank],raports_12[[#This Row],[Bank]],operations[Product],raports_12[[#This Row],[Product]],operations[Month],$B$12) -> 1320 | E4: =raports_12[[#This Row],[Opening balance]]+raports_12[[#This Row],[Operation]] -> 1920 | G4: Entertainment | H4: =SUMIFS(operations[Amount],operations[Category],Expenses12[[#This Row],[Category]],operations[Month],'1'!$B$12) -> -85 | J4: Transportation | K4: =SUMIFS(operations[Amount],operations[Category],Table916283236404448525660[[#This Row],[Category]],operations[Month],'1'!$B$12) -> -80 | N4: Expense
A5: Santander | B5: Credit card | C5: 0 | D5: =SUMIFS(operations[Amount],operations[Bank],raports_12[[#This Row],[Bank]],operations[Product],raports_12[[#This Row],[Product]],operations[Month],$B$12) -> 0 | E5: =raports_12[[#This Row],[Opening balance]]+raports_12[[#This Row],[Operation]] -> 0 | G5: Groceries | H5: =SUMIFS(operations[Amount],operations[Category],Expenses12[[#This Row],[Category]],operations[Month],'1'!$B$12) -> -1715 | J5: Allowance | K5: =SUMIFS(operations[Amount],operations[Category],Table916283236404448525660[[#This Row],[Category]],operations[Month],'1'!$B$12) -> 250 | N5: Expense
A6: Santander | B6: Fixed-term deposit | C6: 2000 | D6: =SUMIFS(operations[Amount],operations[Bank],raports_12[[#This Row],[Bank]],operations[Product],raports_12[[#This Row],[Product]],operations[Month],$B$12) -> 0 | E6: =raports_12[[#This Row],[Opening balance]]+raports_12[[#This Row],[Operation]] -> 2000 | G6: Health&Beauty | H6: =SUMIFS(operations[Amount],operations[Category],Expenses12[[#This Row],[Category]],operations[Month],'1'!$B$12) -> -100 | J6: Financial | K6: =SUMIFS(operations[Amount],operations[Category],Table916283236404448525660[[#This Row],[Category]],operations[Month],'1'!$B$12) -> 105.5 | N6: Expense
A7: Wallet | B7: Gift card | C7: 200 | D7: =SUMIFS(operations[Amount],operations[Bank],raports_12[[#This Row],[Bank]],operations[Product],raports_12[[#This Row],[Product]],operations[Month],$B$12) -> 0 | E7: =raports_12[[#This Row],[Opening balance]]+raports_12[[#This Row],[Operation]] -> 200 | G7: Multimedia | H7: =SUMIFS(operations[Amount],operations[Category],Expenses12[[#This Row],[Category]],operations[Month],'1'!$B$12) -> -150 | J7: Gift | K7: =SUMIFS(operations[Amount],operations[Category],Table916283236404448525660[[#This Row],[Category]],operations[Month],'1'!$B$12) -> 0 | N7: Expense
A8: Wallet | B8: Money | C8: 30 | D8: =SUMIFS(operations[Amount],operations[Bank],raports_12[[#This Row],[Bank]],operations[Product],raports_12[[#This Row],[Product]],operations[Month],$B$12) -> 1100 | E8: =raports_12[[#This Row],[Opening balance]]+raports_12[[#This Row],[Operation]] -> 1130 | G8: Total | H8: =SUBTOTAL(109,Expenses12[Total]) -> -4130 | J8: Other incoms | K8: =SUMIFS(operations[Amount],operations[Category],Table916283236404448525660[[#This Row],[Category]],operations[Month],'1'!$B$12) -> 800 | N8: Expense
A9: Total | C9: =SUBTOTAL(109,raports_12[Opening balance]) -> #REF! | D9: =SUBTOTAL(109,raports_12[Operation]) -> 2420 | E9: =SUBTOTAL(109,raports_12[Closing balance]) -> #REF! | J9: Salary | K9: =SUMIFS(operations[Amount],operations[Category],Table916283236404448525660[[#This Row],[Category]],operations[Month],'1'!$B$12) -> 4500 | N9: Expense
J10: Scholarship | K10: =SUMIFS(operations[Amount],operations[Category],Table916283236404448525660[[#This Row],[Category]],operations[Month],'1'!$B$12) -> 0 | N10: Expense
J11: Transfer | K11: =SUMIFS(operations[Amount],operations[Category],Table916283236404448525660[[#This Row],[Category]],operations[Month],'1'!$B$12) -> 0 | N11: Income
A12: Month | B12: {=_xlfn.TEXTAFTER(CELL("filename",A1),"]")} -> 12 | J12: Total | K12: =SUBTOTAL(109,Table916283236404448525660[Total]) -> 5475.5 | N12: Income
N13: Income
A14: Type | B14: Total | N14: Income
A15: Income | B15: =SUMIFS(operations[Amount],operations[Type],balance_12[[#This Row],[Type]],operations[Month],'1'!$B$12) -> 5655.5 | N15: Income
A16: Expense | B16: =SUMIFS(operations[Amount],operations[Type],balance_12[[#This Row],[Type]],operations[Month],'1'!$B$12) -> -4810 | N16: Income
A17: Transfer | B17: =SUMIFS(operations[Amount],operations[Type],balance_12[[#This Row],[Type]],operations[Month],'1'!$B$12) -> 0 | N17: Transfer
A18: Total | B18: =SUBTOTAL(109,balance_12[Total]) -> 845.5

Sheet 11
A1: Bank | B1: Product | C1: Opening balance | D1: Operation | E1: Closing balance | G1: Category | H1: Total | J1: Category | K1: Total | N1: Type
A2: Millennium | B2: Account | C2: {=INDIRECT("raport_"&$B$12-1&"[@[Closing balance ]]")} -> #REF! | D2: =SUMIFS(operations[Amount],operations[Bank],raports_11[[#This Row],[Bank]],operations[Product],raports_11[[#This Row],[Product]],operations[Month],$B$12) -> 0 | E2: =raports_11[[#This Row],[Opening balance]]+raports_11[[#This Row],[Operation]] -> #REF! | G2: Accomodation | H2: =SUMIFS(operations[Amount],operations[Category],Expenses11[[#This Row],[Category]],operations[Month],'1'!$B$12) -> -2000 | J2: Other expences | N2: Expense
A3: Millennium | B3: Savings account | C3: 10.5 | D3: =SUMIFS(operations[Amount],operations[Bank],raports_11[[#This Row],[Bank]],operations[Product],raports_11[[#This Row],[Product]],operations[Month],$B$12) -> 0 | E3: =raports_11[[#This Row],[Opening balance]]+raports_11[[#This Row],[Operation]] -> 10.5 | G3: Clothing | H3: =SUMIFS(operations[Amount],operations[Category],Expenses11[[#This Row],[Category]],operations[Month],'1'!$B$12) -> -80 | J3: Studies | K3: =SUMIFS(operations[Amount],operations[Category],Table9162832364044485256[[#This Row],[Category]],operations[Month],'1'!$B$12) -> -100 | N3: Expense
A4: Santander | B4: Account | C4: 600 | D4: =SUMIFS(operations[Amount],operations[Bank],raports_11[[#This Row],[Bank]],operations[Product],raports_11[[#This Row],[Product]],operations[Month],$B$12) -> 960 | E4: =raports_11[[#This Row],[Opening balance]]+raports_11[[#This Row],[Operation]] -> 1560 | G4: Entertainment | H4: =SUMIFS(operations[Amount],operations[Category],Expenses11[[#This Row],[Category]],operations[Month],'1'!$B$12) -> -85 | J4: Transportation | K4: =SUMIFS(operations[Amount],operations[Category],Table9162832364044485256[[#This Row],[Category]],operations[Month],'1'!$B$12) -> -80 | N4: Expense
A5: Santander | B5: Credit card | C5: 0 | D5: =SUMIFS(operations[Amount],operations[Bank],raports_11[[#This Row],[Bank]],operations[Product],raports_11[[#This Row],[Product]],operations[Month],$B$12) -> 40 | E5: =raports_11[[#This Row],[Opening balance]]+raports_11[[#This Row],[Operation]] -> 40 | G5: Groceries | H5: =SUMIFS(operations[Amount],operations[Category],Expenses11[[#This Row],[Category]],operations[Month],'1'!$B$12) -> -1715 | J5: Allowance | K5: =SUMIFS(operations[Amount],operations[Category],Table9162832364044485256[[#This Row],[Category]],operations[Month],'1'!$B$12) -> 250 | N5: Expense
A6: Santander | B6: Fixed-term deposit | C6: 2000 | D6: =SUMIFS(operations[Amount],operations[Bank],raports_11[[#This Row],[Bank]],operations[Product],raports_11[[#This Row],[Product]],operations[Month],$B$12) -> 0 | E6: =raports_11[[#This Row],[Opening balance]]+raports_11[[#This Row],[Operation]] -> 2000 | G6: Health&Beauty | H6: =SUMIFS(operations[Amount],operations[Category],Expenses11[[#This Row],[Category]],operations[Month],'1'!$B$12) -> -100 | J6: Financial | K6: =SUMIFS(operations[Amount],operations[Category],Table9162832364044485256[[#This Row],[Category]],operations[Month],'1'!$B$12) -> 105.5 | N6: Expense
A7: Wallet | B7: Gift card | C7: 200 | D7: =SUMIFS(operations[Amount],operations[Bank],raports_11[[#This Row],[Bank]],operations[Product],raports_11[[#This Row],[Product]],operations[Month],$B$12) -> 0 | E7: =raports_11[[#This Row],[Opening balance]]+raports_11[[#This Row],[Operation]] -> 200 | G7: Multimedia | H7: =SUMIFS(operations[Amount],operations[Category],Expenses11[[#This Row],[Category]],operations[Month],'1'!$B$12) -> -150 | J7: Gift | K7: =SUMIFS(operations[Amount],operations[Category],Table9162832364044485256[[#This Row],[Category]],operations[Month],'1'!$B$12) -> 0 | N7: Expense
A8: Wallet | B8: Money | C8: 30 | D8: =SUMIFS(operations[Amount],operations[Bank],raports_11[[#This Row],[Bank]],operations[Product],raports_11[[#This Row],[Product]],operations[Month],$B$12) -> 400 | E8: =raports_11[[#This Row],[Opening balance]]+raports_11[[#This Row],[Operation]] -> 430 | G8: Total | H8: =SUBTOTAL(109,Expenses11[Total]) -> -4130 | J8: Other incoms | K8: =SUMIFS(operations[Amount],operations[Category],Table9162832364044485256[[#This Row],[Category]],operations[Month],'1'!$B$12) -> 800 | N8: Expense
A9: Total | C9: =SUBTOTAL(109,raports_11[Opening balance]) -> #REF! | D9: =SUBTOTAL(109,raports_11[Operation]) -> 1400 | E9: =SUBTOTAL(109,raports_11[Closing balance]) -> #REF! | J9: Salary | K9: =SUMIFS(operations[Amount],operations[Category],Table9162832364044485256[[#This Row],[Category]],operations[Month],'1'!$B$12) -> 4500 | N9: Expense
J10: Scholarship | K10: =SUMIFS(operations[Amount],operations[Category],Table9162832364044485256[[#This Row],[Category]],operations[Month],'1'!$B$12) -> 0 | N10: Expense
J11: Transfer | K11: =SUMIFS(operations[Amount],operations[Category],Table9162832364044485256[[#This Row],[Category]],operations[Month],'1'!$B$12) -> 0 | N11: Income
A12: Month | B12: {=_xlfn.TEXTAFTER(CELL("filename",A1),"]")} -> 11 | J12: Total | K12: =SUBTOTAL(109,Table9162832364044485256[Total]) -> 5475.5 | N12: Income
N13: Income
A14: Type | B14: Total | N14: Income
A15: Income | B15: =SUMIFS(operations[Amount],operations[Type],balance_11[[#This Row],[Type]],operations[Month],'1'!$B$12) -> 5655.5 | N15: Income
A16: Expense | B16: =SUMIFS(operations[Amount],operations[Type],balance_11[[#This Row],[Type]],operations[Month],'1'!$B$12) -> -4810 | N16: Income
A17: Transfer | B17: =SUMIFS(operations[Amount],operations[Type],balance_11[[#This Row],[Type]],operations[Month],'1'!$B$12) -> 0 | N17: Transfer
A18: Total | B18: =SUBTOTAL(109,balance_11[Total]) -> 845.5

Sheet 9
A1: Bank | B1: Product | C1: Opening balance | D1: Operation | E1: Closing balance | G1: Category | H1: Total | J1: Category | K1: Total | N1: Type
A2: Millennium | B2: Account | C2: {=INDIRECT("raport_"&$B$12-1&"[@[Closing balance ]]")} -> #REF! | D2: =SUMIFS(operations[Amount],operations[Bank],raports_9[[#This Row],[Bank]],operations[Product],raports_9[[#This Row],[Product]],operations[Month],$B$12) -> -20 | E2: =raports_9[[#This Row],[Opening balance]]+raports_9[[#This Row],[Operation]] -> #REF! | G2: Accomodation | H2: =SUMIFS(operations[Amount],operations[Category],Expenses9[[#This Row],[Category]],operations[Month],'1'!$B$12) -> -2000 | J2: Other expences | N2: Expense
A3: Millennium | B3: Savings account | C3: 10.5 | D3: =SUMIFS(operations[Amount],operations[Bank],raports_9[[#This Row],[Bank]],operations[Product],raports_9[[#This Row],[Product]],operations[Month],$B$12) -> 0 | E3: =raports_9[[#This Row],[Opening balance]]+raports_9[[#This Row],[Operation]] -> 10.5 | G3: Clothing | H3: =SUMIFS(operations[Amount],operations[Category],Expenses9[[#This Row],[Category]],operations[Month],'1'!$B$12) -> -80 | J3: Studies | K3: =SUMIFS(operations[Amount],operations[Category],Table916283236404448[[#This Row],[Category]],operations[Month],'1'!$B$12) -> -100 | N3: Expense
A4: Santander | B4: Account | C4: 600 | D4: =SUMIFS(operations[Amount],operations[Bank],raports_9[[#This Row],[Bank]],operations[Product],raports_9[[#This Row],[Product]],operations[Month],$B$12) -> 1689.5 | E4: =raports_9[[#This Row],[Opening balance]]+raports_9[[#This Row],[Operation]] -> 2289.5 | G4: Entertainment | H4: =SUMIFS(operations[Amount],operations[Category],Expenses9[[#This Row],[Category]],operations[Month],'1'!$B$12) -> -85 | J4: Transportation | K4: =SUMIFS(operations[Amount],operations[Category],Table916283236404448[[#This Row],[Category]],operations[Month],'1'!$B$12) -> -80 | N4: Expense
A5: Santander | B5: Credit card | C5: 0 | D5: =SUMIFS(operations[Amount],operations[Bank],raports_9[[#This Row],[Bank]],operations[Product],raports_9[[#This Row],[Product]],operations[Month],$B$12) -> 82 | E5: =raports_9[[#This Row],[Opening balance]]+raports_9[[#This Row],[Operation]] -> 82 | G5: Groceries | H5: =SUMIFS(operations[Amount],operations[Category],Expenses9[[#This Row],[Category]],operations[Month],'1'!$B$12) -> -1715 | J5: Allowance | K5: =SUMIFS(operations[Amount],operations[Category],Table916283236404448[[#This Row],[Category]],operations[Month],'1'!$B$12) -> 250 | N5: Expense
A6: Santander | B6: Fixed-term deposit | C6: 2000 | D6: =SUMIFS(operations[Amount],operations[Bank],raports_9[[#This Row],[Bank]],operations[Product],raports_9[[#This Row],[Product]],operations[Month],$B$12) -> 0 | E6: =raports_9[[#This Row],[Opening balance]]+raports_9[[#This Row],[Operation]] -> 2000 | G6: Health&Beauty | H6: =SUMIFS(operations[Amount],operations[Category],Expenses9[[#This Row],[Category]],operations[Month],'1'!$B$12) -> -100 | J6: Financial | K6: =SUMIFS(operations[Amount],operations[Category],Table916283236404448[[#This Row],[Category]],operations[Month],'1'!$B$12) -> 105.5 | N6: Expense
A7: Wallet | B7: Gift card | C7: 200 | D7: =SUMIFS(operations[Amount],operations[Bank],raports_9[[#This Row],[Bank]],operations[Product],raports_9[[#This Row],[Product]],operations[Month],$B$12) -> 0 | E7: =raports_9[[#This Row],[Opening balance]]+raports_9[[#This Row],[Operation]] -> 200 | G7: Multimedia | H7: =SUMIFS(operations[Amount],operations[Category],Expenses9[[#This Row],[Category]],operations[Month],'1'!$B$12) -> -150 | J7: Gift | K7: =SUMIFS(operations[Amount],operations[Category],Table916283236404448[[#This Row],[Category]],operations[Month],'1'!$B$12) -> 0 | N7: Expense
A8: Wallet | B8: Money | C8: 30 | D8: =SUMIFS(operations[Amount],operations[Bank],raports_9[[#This Row],[Bank]],operations[Product],raports_9[[#This Row],[Product]],operations[Month],$B$12) -> 0 | E8: =raports_9[[#This Row],[Opening balance]]+raports_9[[#This Row],[Operation]] -> 30 | G8: Total | H8: =SUBTOTAL(109,Expenses9[Total]) -> -4130 | J8: Other incoms | K8: =SUMIFS(operations[Amount],operations[Category],Table916283236404448[[#This Row],[Category]],operations[Month],'1'!$B$12) -> 800 | N8: Expense
A9: Total | C9: =SUBTOTAL(109,raports_9[Opening balance]) -> #REF! | D9: =SUBTOTAL(109,raports_9[Operation]) -> 1751.5 | E9: =SUBTOTAL(109,raports_9[Closing balance]) -> #REF! | J9: Salary | K9: =SUMIFS(operations[Amount],operations[Category],Table916283236404448[[#This Row],[Category]],operations[Month],'1'!$B$12) -> 4500 | N9: Expense
J10: Scholarship | K10: =SUMIFS(operations[Amount],operations[Category],Table916283236404448[[#This Row],[Category]],operations[Month],'1'!$B$12) -> 0 | N10: Expense
J11: Transfer | K11: =SUMIFS(operations[Amount],operations[Category],Table916283236404448[[#This Row],[Category]],operations[Month],'1'!$B$12) -> 0 | N11: Income
A12: Month | B12: {=_xlfn.TEXTAFTER(CELL("filename",A1),"]")} -> 9 | J12: Total | K12: =SUBTOTAL(109,Table916283236404448[Total]) -> 5475.5 | N12: Income
N13: Income
A14: Type | B14: Total | N14: Income
A15: Income | B15: =SUMIFS(operations[Amount],operations[Type],balance_9[[#This Row],[Type]],operations[Month],'1'!$B$12) -> 5655.5 | N15: Income
A16: Expense | B16: =SUMIFS(operations[Amount],operations[Type],balance_9[[#This Row],[Type]],operations[Month],'1'!$B$12) -> -4810 | N16: Income
A17: Transfer | B17: =SUMIFS(operations[Amount],operations[Type],balance_9[[#This Row],[Type]],operations[Month],'1'!$B$12) -> 0 | N17: Transfer
A18: Total | B18: =SUBTOTAL(109,balance_9[Total]) -> 845.5

Sheet 10
A1: Bank | B1: Product | C1: Opening balance | D1: Operation | E1: Closing balance | G1: Category | H1: Total | J1: Category | K1: Total | N1: Type
A2: Millennium | B2: Account | C2: {=INDIRECT("raport_"&$B$12-1&"[@[Closing balance ]]")} -> #REF! | D2: =SUMIFS(operations[Amount],operations[Bank],raports_10[[#This Row],[Bank]],operations[Product],raports_10[[#This Row],[Product]],operations[Month],$B$12) -> 0 | E2: =raports_10[[#This Row],[Opening balance]]+raports_10[[#This Row],[Operation]] -> #REF! | G2: Accomodation | H2: =SUMIFS(operations[Amount],operations[Category],Expenses10[[#This Row],[Category]],operations[Month],'1'!$B$12) -> -2000 | J2: Other expences | N2: Expense
A3: Millennium | B3: Savings account | C3: 10.5 | D3: =SUMIFS(operations[Amount],operations[Bank],raports_10[[#This Row],[Bank]],operations[Product],raports_10[[#This Row],[Product]],operations[Month],$B$12) -> 0 | E3: =raports_10[[#This Row],[Opening balance]]+raports_10[[#This Row],[Operation]] -> 10.5 | G3: Clothing | H3: =SUMIFS(operations[Amount],operations[Category],Expenses10[[#This Row],[Category]],operations[Month],'1'!$B$12) -> -80 | J3: Studies | K3: =SUMIFS(operations[Amount],operations[Category],Table91628323640444852[[#This Row],[Category]],operations[Month],'1'!$B$12) -> -100 | N3: Expense
A4: Santander | B4: Account | C4: 600 | D4: =SUMIFS(operations[Amount],operations[Bank],raports_10[[#This Row],[Bank]],operations[Product],raports_10[[#This Row],[Product]],operations[Month],$B$12) -> 1690 | E4: =raports_10[[#This Row],[Opening balance]]+raports_10[[#This Row],[Operation]] -> 2290 | G4: Entertainment | H4: =SUMIFS(operations[Amount],operations[Category],Expenses10[[#This Row],[Category]],operations[Month],'1'!$B$12) -> -85 | J4: Transportation | K4: =SUMIFS(operations[Amount],operations[Category],Table91628323640444852[[#This Row],[Category]],operations[Month],'1'!$B$12) -> -80 | N4: Expense
A5: Santander | B5: Credit card | C5: 0 | D5: =SUMIFS(operations[Amount],operations[Bank],raports_10[[#This Row],[Bank]],operations[Product],raports_10[[#This Row],[Product]],operations[Month],$B$12) -> -20 | E5: =raports_10[[#This Row],[Opening balance]]+raports_10[[#This Row],[Operation]] -> -20 | G5: Groceries | H5: =SUMIFS(operations[Amount],operations[Category],Expenses10[[#This Row],[Category]],operations[Month],'1'!$B$12) -> -1715 | J5: Allowance | K5: =SUMIFS(operations[Amount],operations[Category],Table91628323640444852[[#This Row],[Category]],operations[Month],'1'!$B$12) -> 250 | N5: Expense
A6: Santander | B6: Fixed-term deposit | C6: 2000 | D6: =SUMIFS(operations[Amount],operations[Bank],raports_10[[#This Row],[Bank]],operations[Product],raports_10[[#This Row],[Product]],operations[Month],$B$12) -> 0 | E6: =raports_10[[#This Row],[Opening balance]]+raports_10[[#This Row],[Operation]] -> 2000 | G6: Health&Beauty | H6: =SUMIFS(operations[Amount],operations[Category],Expenses10[[#This Row],[Category]],operations[Month],'1'!$B$12) -> -100 | J6: Financial | K6: =SUMIFS(operations[Amount],operations[Category],Table91628323640444852[[#This Row],[Category]],operations[Month],'1'!$B$12) -> 105.5 | N6: Expense
A7: Wallet | B7: Gift card | C7: 200 | D7: =SUMIFS(operations[Amount],operations[Bank],raports_10[[#This Row],[Bank]],operations[Product],raports_10[[#This Row],[Product]],operations[Month],$B$12) -> 0 | E7: =raports_10[[#This Row],[Opening balance]]+raports_10[[#This Row],[Operation]] -> 200 | G7: Multimedia | H7: =SUMIFS(operations[Amount],operations[Category],Expenses10[[#This Row],[Category]],operations[Month],'1'!$B$12) -> -150 | J7: Gift | K7: =SUMIFS(operations[Amount],operations[Category],Table91628323640444852[[#This Row],[Category]],operations[Month],'1'!$B$12) -> 0 | N7: Expense
A8: Wallet | B8: Money | C8: 30 | D8: =SUMIFS(operations[Amount],operations[Bank],raports_10[[#This Row],[Bank]],operations[Product],raports_10[[#This Row],[Product]],operations[Month],$B$12) -> 0 | E8: =raports_10[[#This Row],[Opening balance]]+raports_10[[#This Row],[Operation]] -> 30 | G8: Total | H8: =SUBTOTAL(109,Expenses10[Total]) -> -4130 | J8: Other incoms | K8: =SUMIFS(operations[Amount],operations[Category],Table91628323640444852[[#This Row],[Category]],operations[Month],'1'!$B$12) -> 800 | N8: Expense
A9: Total | C9: =SUBTOTAL(109,raports_10[Opening balance]) -> #REF! | D9: =SUBTOTAL(109,raports_10[Operation]) -> 1670 | E9: =SUBTOTAL(109,raports_10[Closing balance]) -> #REF! | J9: Salary | K9: =SUMIFS(operations[Amount],operations[Category],Table91628323640444852[[#This Row],[Category]],operations[Month],'1'!$B$12) -> 4500 | N9: Expense
J10: Scholarship | K10: =SUMIFS(operations[Amount],operations[Category],Table91628323640444852[[#This Row],[Category]],operations[Month],'1'!$B$12) -> 0 | N10: Expense
J11: Transfer | K11: =SUMIFS(operations[Amount],operations[Category],Table91628323640444852[[#This Row],[Category]],operations[Month],'1'!$B$12) -> 0 | N11: Income
A12: Month | B12: {=_xlfn.TEXTAFTER(CELL("filename",A1),"]")} -> 10 | J12: Total | K12: =SUBTOTAL(109,Table91628323640444852[Total]) -> 5475.5 | N12: Income
N13: Income
A14: Type | B14: Total | N14: Income
A15: Income | B15: =SUMIFS(operations[Amount],operations[Type],balance_10[[#This Row],[Type]],operations[Month],'1'!$B$12) -> 5655.5 | N15: Income
A16: Expense | B16: =SUMIFS(operations[Amount],operations[Type],balance_10[[#This Row],[Type]],operations[Month],'1'!$B$12) -> -4810 | N16: Income
A17: Transfer | B17: =SUMIFS(operations[Amount],operations[Type],balance_10[[#This Row],[Type]],operations[Month],'1'!$B$12) -> 0 | N17: Transfer
A18: Total | B18: =SUBTOTAL(109,balance_10[Total]) -> 845.5

Sheet 8
A1: Bank | B1: Product | C1: Opening balance | D1: Operation | E1: Closing balance | G1: Category | H1: Total | J1: Category | K1: Total | N1: Type
A2: Millennium | B2: Account | C2: {=INDIRECT("raport_"&$B$12-1&"[@[Closing balance ]]")} -> #REF! | D2: =SUMIFS(operations[Amount],operations[Bank],raports_8[[#This Row],[Bank]],operations[Product],raports_8[[#This Row],[Product]],operations[Month],$B$12) -> 200 | E2: =raports_8[[#This Row],[Opening balance]]+raports_8[[#This Row],[Operation]] -> #REF! | G2: Accomodation | H2: =SUMIFS(operations[Amount],operations[Category],Expenses8[[#This Row],[Category]],operations[Month],'1'!$B$12) -> -2000 | J2: Other expences | N2: Expense
A3: Millennium | B3: Savings account | C3: 10.5 | D3: =SUMIFS(operations[Amount],operations[Bank],raports_8[[#This Row],[Bank]],operations[Product],raports_8[[#This Row],[Product]],operations[Month],$B$12) -> -300 | E3: =raports_8[[#This Row],[Opening balance]]+raports_8[[#This Row],[Operation]] -> -289.5 | G3: Clothing | H3: =SUMIFS(operations[Amount],operations[Category],Expenses8[[#This Row],[Category]],operations[Month],'1'!$B$12) -> -80 | J3: Studies | K3: =SUMIFS(operations[Amount],operations[Category],Table9162832364044[[#This Row],[Category]],operations[Month],'1'!$B$12) -> -100 | N3: Expense
A4: Santander | B4: Account | C4: 600 | D4: =SUMIFS(operations[Amount],operations[Bank],raports_8[[#This Row],[Bank]],operations[Product],raports_8[[#This Row],[Product]],operations[Month],$B$12) -> 1475 | E4: =raports_8[[#This Row],[Opening balance]]+raports_8[[#This Row],[Operation]] -> 2075 | G4: Entertainment | H4: =SUMIFS(operations[Amount],operations[Category],Expenses8[[#This Row],[Category]],operations[Month],'1'!$B$12) -> -85 | J4: Transportation | K4: =SUMIFS(operations[Amount],operations[Category],Table9162832364044[[#This Row],[Category]],operations[Month],'1'!$B$12) -> -80 | N4: Expense
A5: Santander | B5: Credit card | C5: 0 | D5: =SUMIFS(operations[Amount],operations[Bank],raports_8[[#This Row],[Bank]],operations[Product],raports_8[[#This Row],[Product]],operations[Month],$B$12) -> 33 | E5: =raports_8[[#This Row],[Opening balance]]+raports_8[[#This Row],[Operation]] -> 33 | G5: Groceries | H5: =SUMIFS(operations[Amount],operations[Category],Expenses8[[#This Row],[Category]],operations[Month],'1'!$B$12) -> -1715 | J5: Allowance | K5: =SUMIFS(operations[Amount],operations[Category],Table9162832364044[[#This Row],[Category]],operations[Month],'1'!$B$12) -> 250 | N5: Expense
A6: Santander | B6: Fixed-term deposit | C6: 2000 | D6: =SUMIFS(operations[Amount],operations[Bank],raports_8[[#This Row],[Bank]],operations[Product],raports_8[[#This Row],[Product]],operations[Month],$B$12) -> -1020 | E6: =raports_8[[#This Row],[Opening balance]]+raports_8[[#This Row],[Operation]] -> 980 | G6: Health&Beauty | H6: =SUMIFS(operations[Amount],operations[Category],Expenses8[[#This Row],[Category]],operations[Month],'1'!$B$12) -> -100 | J6: Financial | K6: =SUMIFS(operations[Amount],operations[Category],Table9162832364044[[#This Row],[Category]],operations[Month],'1'!$B$12) -> 105.5 | N6: Expense
A7: Wallet | B7: Gift card | C7: 200 | D7: =SUMIFS(operations[Amount],operations[Bank],raports_8[[#This Row],[Bank]],operations[Product],raports_8[[#This Row],[Product]],operations[Month],$B$12) -> 0 | E7: =raports_8[[#This Row],[Opening balance]]+raports_8[[#This Row],[Operation]] -> 200 | G7: Multimedia | H7: =SUMIFS(operations[Amount],operations[Category],Expenses8[[#This Row],[Category]],operations[Month],'1'!$B$12) -> -150 | J7: Gift | K7: =SUMIFS(operations[Amount],operations[Category],Table9162832364044[[#This Row],[Category]],operations[Month],'1'!$B$12) -> 0 | N7: Expense
A8: Wallet | B8: Money | C8: 30 | D8: =SUMIFS(operations[Amount],operations[Bank],raports_8[[#This Row],[Bank]],operations[Product],raports_8[[#This Row],[Product]],operations[Month],$B$12) -> 2.5 | E8: =raports_8[[#This Row],[Opening balance]]+raports_8[[#This Row],[Operation]] -> 32.5 | G8: Total | H8: =SUBTOTAL(109,Expenses8[Total]) -> -4130 | J8: Other incoms | K8: =SUMIFS(operations[Amount],operations[Category],Table9162832364044[[#This Row],[Category]],operations[Month],'1'!$B$12) -> 800 | N8: Expense
A9: Total | C9: =SUBTOTAL(109,raports_8[Opening balance]) -> #REF! | D9: =SUBTOTAL(109,raports_8[Operation]) -> 390.5 | E9: =SUBTOTAL(109,raports_8[Closing balance]) -> #REF! | J9: Salary | K9: =SUMIFS(operations[Amount],operations[Category],Table9162832364044[[#This Row],[Category]],operations[Month],'1'!$B$12) -> 4500 | N9: Expense
J10: Scholarship | K10: =SUMIFS(operations[Amount],operations[Category],Table9162832364044[[#This Row],[Category]],operations[Month],'1'!$B$12) -> 0 | N10: Expense
J11: Transfer | K11: =SUMIFS(operations[Amount],operations[Category],Table9162832364044[[#This Row],[Category]],operations[Month],'1'!$B$12) -> 0 | N11: Income
A12: Month | B12: {=_xlfn.TEXTAFTER(CELL("filename",A1),"]")} -> 8 | J12: Total | K12: =SUBTOTAL(109,Table9162832364044[Total]) -> 5475.5 | N12: Income
N13: Income
A14: Type | B14: Total | N14: Income
A15: Income | B15: =SUMIFS(operations[Amount],operations[Type],balance_8[[#This Row],[Type]],operations[Month],'1'!$B$12) -> 5655.5 | N15: Income
A16: Expense | B16: =SUMIFS(operations[Amount],operations[Type],balance_8[[#This Row],[Type]],operations[Month],'1'!$B$12) -> -4810 | N16: Income
A17: Transfer | B17: =SUMIFS(operations[Amount],operations[Type],balance_8[[#This Row],[Type]],operations[Month],'1'!$B$12) -> 0 | N17: Transfer
A18: Total | B18: =SUBTOTAL(109,balance_8[Total]) -> 845.5

Sheet 7
A1: Bank | B1: Product | C1: Opening balance | D1: Operation | E1: Closing balance | G1: Category | H1: Total | J1: Category | K1: Total | N1: Type
A2: Millennium | B2: Account | C2: {=INDIRECT("raport_"&$B$12-1&"[@[Closing balance ]]")} -> #REF! | D2: =SUMIFS(operations[Amount],operations[Bank],raports_7[[#This Row],[Bank]],operations[Product],raports_7[[#This Row],[Product]],operations[Month],$B$12) -> -100 | E2: =raports_7[[#This Row],[Opening balance]]+raports_7[[#This Row],[Operation]] -> #REF! | G2: Accomodation | H2: =SUMIFS(operations[Amount],operations[Category],Expenses7[[#This Row],[Category]],operations[Month],'1'!$B$12) -> -2000 | J2: Other expences | N2: Expense
A3: Millennium | B3: Savings account | C3: 10.5 | D3: =SUMIFS(operations[Amount],operations[Bank],raports_7[[#This Row],[Bank]],operations[Product],raports_7[[#This Row],[Product]],operations[Month],$B$12) -> 1050 | E3: =raports_7[[#This Row],[Opening balance]]+raports_7[[#This Row],[Operation]] -> 1060.5 | G3: Clothing | H3: =SUMIFS(operations[Amount],operations[Category],Expenses7[[#This Row],[Category]],operations[Month],'1'!$B$12) -> -80 | J3: Studies | K3: =SUMIFS(operations[Amount],operations[Category],Table91628323640[[#This Row],[Category]],operations[Month],'1'!$B$12) -> -100 | N3: Expense
A4: Santander | B4: Account | C4: 600 | D4: =SUMIFS(operations[Amount],operations[Bank],raports_7[[#This Row],[Bank]],operations[Product],raports_7[[#This Row],[Product]],operations[Month],$B$12) -> 1010 | E4: =raports_7[[#This Row],[Opening balance]]+raports_7[[#This Row],[Operation]] -> 1610 | G4: Entertainment | H4: =SUMIFS(operations[Amount],operations[Category],Expenses7[[#This Row],[Category]],operations[Month],'1'!$B$12) -> -85 | J4: Transportation | K4: =SUMIFS(operations[Amount],operations[Category],Table91628323640[[#This Row],[Category]],operations[Month],'1'!$B$12) -> -80 | N4: Expense
A5: Santander | B5: Credit card | C5: 0 | D5: =SUMIFS(operations[Amount],operations[Bank],raports_7[[#This Row],[Bank]],operations[Product],raports_7[[#This Row],[Product]],operations[Month],$B$12) -> 1165 | E5: =raports_7[[#This Row],[Opening balance]]+raports_7[[#This Row],[Operation]] -> 1165 | G5: Groceries | H5: =SUMIFS(operations[Amount],operations[Category],Expenses7[[#This Row],[Category]],operations[Month],'1'!$B$12) -> -1715 | J5: Allowance | K5: =SUMIFS(operations[Amount],operations[Category],Table91628323640[[#This Row],[Category]],operations[Month],'1'!$B$12) -> 250 | N5: Expense
A6: Santander | B6: Fixed-term deposit | C6: 2000 | D6: =SUMIFS(operations[Amount],operations[Bank],raports_7[[#This Row],[Bank]],operations[Product],raports_7[[#This Row],[Product]],operations[Month],$B$12) -> -180 | E6: =raports_7[[#This Row],[Opening balance]]+raports_7[[#This Row],[Operation]] -> 1820 | G6: Health&Beauty | H6: =SUMIFS(operations[Amount],operations[Category],Expenses7[[#This Row],[Category]],operations[Month],'1'!$B$12) -> -100 | J6: Financial | K6: =SUMIFS(operations[Amount],operations[Category],Table91628323640[[#This Row],[Category]],operations[Month],'1'!$B$12) -> 105.5 | N6: Expense
A7: Wallet | B7: Gift card | C7: 200 | D7: =SUMIFS(operations[Amount],operations[Bank],raports_7[[#This Row],[Bank]],operations[Product],raports_7[[#This Row],[Product]],operations[Month],$B$12) -> -30 | E7: =raports_7[[#This Row],[Opening balance]]+raports_7[[#This Row],[Operation]] -> 170 | G7: Multimedia | H7: =SUMIFS(operations[Amount],operations[Category],Expenses7[[#This Row],[Category]],operations[Month],'1'!$B$12) -> -150 | J7: Gift | K7: =SUMIFS(operations[Amount],operations[Category],Table91628323640[[#This Row],[Category]],operations[Month],'1'!$B$12) -> 0 | N7: Expense
A8: Wallet | B8: Money | C8: 30 | D8: =SUMIFS(operations[Amount],operations[Bank],raports_7[[#This Row],[Bank]],operations[Product],raports_7[[#This Row],[Product]],operations[Month],$B$12) -> 0 | E8: =raports_7[[#This Row],[Opening balance]]+raports_7[[#This Row],[Operation]] -> 30 | G8: Total | H8: =SUBTOTAL(109,Expenses7[Total]) -> -4130 | J8: Other incoms | K8: =SUMIFS(operations[Amount],operations[Category],Table91628323640[[#This Row],[Category]],operations[Month],'1'!$B$12) -> 800 | N8: Expense
A9: Total | C9: =SUBTOTAL(109,raports_7[Opening balance]) -> #REF! | D9: =SUBTOTAL(109,raports_7[Operation]) -> 2915 | E9: =SUBTOTAL(109,raports_7[Closing balance]) -> #REF! | J9: Salary | K9: =SUMIFS(operations[Amount],operations[Category],Table91628323640[[#This Row],[Category]],operations[Month],'1'!$B$12) -> 4500 | N9: Expense
J10: Scholarship | K10: =SUMIFS(operations[Amount],operations[Category],Table91628323640[[#This Row],[Category]],operations[Month],'1'!$B$12) -> 0 | N10: Expense
J11: Transfer | K11: =SUMIFS(operations[Amount],operations[Category],Table91628323640[[#This Row],[Category]],operations[Month],'1'!$B$12) -> 0 | N11: Income
A12: Month | B12: {=_xlfn.TEXTAFTER(CELL("filename",A1),"]")} -> 7 | J12: Total | K12: =SUBTOTAL(109,Table91628323640[Total]) -> 5475.5 | N12: Income
N13: Income
A14: Type | B14: Total | N14: Income
A15: Income | B15: =SUMIFS(operations[Amount],operations[Type],balance_7[[#This Row],[Type]],operations[Month],'1'!$B$12) -> 5655.5 | N15: Income
A16: Expense | B16: =SUMIFS(operations[Amount],operations[Type],balance_7[[#This Row],[Type]],operations[Month],'1'!$B$12) -> -4810 | N16: Income
A17: Transfer | B17: =SUMIFS(operations[Amount],operations[Type],balance_7[[#This Row],[Type]],operations[Month],'1'!$B$12) -> 0 | N17: Transfer
A18: Total | B18: =SUBTOTAL(109,balance_7[Total]) -> 845.5

Sheet 6
A1: Bank | B1: Product | C1: Opening balance | D1: Operation | E1: Closing balance | G1: Category | H1: Total | J1: Category | K1: Total | N1: Type
A2: Millennium | B2: Account | C2: {=INDIRECT("raports_"&$B$12-1&"[@[Closing balance ]]")} -> #REF! | D2: =SUMIFS(operations[Amount],operations[Bank],raports_5[[#This Row],[Bank]],operations[Product],raports_5[[#This Row],[Product]],operations[Month],$B$12) -> 250 | E2: =raports_5[[#This Row],[Opening balance]]+raports_5[[#This Row],[Operation]] -> #REF! | G2: Accomodation | H2: =SUMIFS(operations[Amount],operations[Category],Expenses6[[#This Row],[Category]],operations[Month],'1'!$B$12) -> -2000 | J2: Other expences | N2: Expense
A3: Millennium | B3: Savings account | C3: 10.5 | D3: =SUMIFS(operations[Amount],operations[Bank],raports_5[[#This Row],[Bank]],operations[Product],raports_5[[#This Row],[Product]],operations[Month],$B$12) -> 0 | E3: =raports_5[[#This Row],[Opening balance]]+raports_5[[#This Row],[Operation]] -> 10.5 | G3: Clothing | H3: =SUMIFS(operations[Amount],operations[Category],Expenses6[[#This Row],[Category]],operations[Month],'1'!$B$12) -> -80 | J3: Studies | K3: =SUMIFS(operations[Amount],operations[Category],Table916283236[[#This Row],[Category]],operations[Month],'1'!$B$12) -> -100 | N3: Expense
A4: Santander | B4: Account | C4: 600 | D4: =SUMIFS(operations[Amount],operations[Bank],raports_5[[#This Row],[Bank]],operations[Product],raports_5[[#This Row],[Product]],operations[Month],$B$12) -> 1420 | E4: =raports_5[[#This Row],[Opening balance]]+raports_5[[#This Row],[Operation]] -> 2020 | G4: Entertainment | H4: =SUMIFS(operations[Amount],operations[Category],Expenses6[[#This Row],[Category]],operations[Month],'1'!$B$12) -> -85 | J4: Transportation | K4: =SUMIFS(operations[Amount],operations[Category],Table916283236[[#This Row],[Category]],operations[Month],'1'!$B$12) -> -80 | N4: Expense
A5: Santander | B5: Credit card | C5: 0 | D5: =SUMIFS(operations[Amount],operations[Bank],raports_5[[#This Row],[Bank]],operations[Product],raports_5[[#This Row],[Product]],operations[Month],$B$12) -> -300 | E5: =raports_5[[#This Row],[Opening balance]]+raports_5[[#This Row],[Operation]] -> -300 | G5: Groceries | H5: =SUMIFS(operations[Amount],operations[Category],Expenses6[[#This Row],[Category]],operations[Month],'1'!$B$12) -> -1715 | J5: Allowance | K5: =SUMIFS(operations[Amount],operations[Category],Table916283236[[#This Row],[Category]],operations[Month],'1'!$B$12) -> 250 | N5: Expense
A6: Santander | B6: Fixed-term deposit | C6: 2000 | D6: =SUMIFS(operations[Amount],operations[Bank],raports_5[[#This Row],[Bank]],operations[Product],raports_5[[#This Row],[Product]],operations[Month],$B$12) -> 0 | E6: =raports_5[[#This Row],[Opening balance]]+raports_5[[#This Row],[Operation]] -> 2000 | G6: Health&Beauty | H6: =SUMIFS(operations[Amount],operations[Category],Expenses6[[#This Row],[Category]],operations[Month],'1'!$B$12) -> -100 | J6: Financial | K6: =SUMIFS(operations[Amount],operations[Category],Table916283236[[#This Row],[Category]],operations[Month],'1'!$B$12) -> 105.5 | N6: Expense
A7: Wallet | B7: Gift card | C7: 200 | D7: =SUMIFS(operations[Amount],operations[Bank],raports_5[[#This Row],[Bank]],operations[Product],raports_5[[#This Row],[Product]],operations[Month],$B$12) -> 0 | E7: =raports_5[[#This Row],[Opening balance]]+raports_5[[#This Row],[Operation]] -> 200 | G7: Multimedia | H7: =SUMIFS(operations[Amount],operations[Category],Expenses6[[#This Row],[Category]],operations[Month],'1'!$B$12) -> -150 | J7: Gift | K7: =SUMIFS(operations[Amount],operations[Category],Table916283236[[#This Row],[Category]],operations[Month],'1'!$B$12) -> 0 | N7: Expense
A8: Wallet | B8: Money | C8: 30 | D8: =SUMIFS(operations[Amount],operations[Bank],raports_5[[#This Row],[Bank]],operations[Product],raports_5[[#This Row],[Product]],operations[Month],$B$12) -> -200 | E8: =raports_5[[#This Row],[Opening balance]]+raports_5[[#This Row],[Operation]] -> -170 | G8: Total | H8: =SUBTOTAL(109,Expenses6[Total]) -> -4130 | J8: Other incoms | K8: =SUMIFS(operations[Amount],operations[Category],Table916283236[[#This Row],[Category]],operations[Month],'1'!$B$12) -> 800 | N8: Expense
A9: Total | C9: =SUBTOTAL(109,raports_5[Opening balance]) -> #REF! | D9: =SUBTOTAL(109,raports_5[Operation]) -> 1170 | E9: =SUBTOTAL(109,raports_5[Closing balance]) -> #REF! | J9: Salary | K9: =SUMIFS(operations[Amount],operations[Category],Table916283236[[#This Row],[Category]],operations[Month],'1'!$B$12) -> 4500 | N9: Expense
J10: Scholarship | K10: =SUMIFS(operations[Amount],operations[Category],Table916283236[[#This Row],[Category]],operations[Month],'1'!$B$12) -> 0 | N10: Expense
J11: Transfer | K11: =SUMIFS(operations[Amount],operations[Category],Table916283236[[#This Row],[Category]],operations[Month],'1'!$B$12) -> 0 | N11: Income
A12: Month | B12: {=_xlfn.TEXTAFTER(CELL("filename",A1),"]")} -> 6 | J12: Total | K12: =SUBTOTAL(109,Table916283236[Total]) -> 5475.5 | N12: Income
N13: Income
A14: Type | B14: Total | N14: Income
A15: Income | B15: =SUMIFS(operations[Amount],operations[Type],balance_6[[#This Row],[Type]],operations[Month],'1'!$B$12) -> 5655.5 | N15: Income
A16: Expense | B16: =SUMIFS(operations[Amount],operations[Type],balance_6[[#This Row],[Type]],operations[Month],'1'!$B$12) -> -4810 | N16: Income
A17: Transfer | B17: =SUMIFS(operations[Amount],operations[Type],balance_6[[#This Row],[Type]],operations[Month],'1'!$B$12) -> 0 | N17: Transfer
A18: Total | B18: =SUBTOTAL(109,balance_6[Total]) -> 845.5

Sheet 5
A1: Bank | B1: Product | C1: Opening balance | D1: Operation | E1: Closing balance | G1: Category | H1: Total | J1: Category | K1: Total | N1: Type
A2: Millennium | B2: Account | C2: {=INDIRECT("raport_"&$B$12-1&"[@[Closing balance ]]")} -> #REF! | D2: =SUMIFS(operations[Amount],operations[Bank],raports_6[[#This Row],[Bank]],operations[Product],raports_6[[#This Row],[Product]],operations[Month],$B$12) -> -50 | E2: =raports_6[[#This Row],[Opening balance]]+raports_6[[#This Row],[Operation]] -> #REF! | G2: Accomodation | H2: =SUMIFS(operations[Amount],operations[Category],Expenses5[[#This Row],[Category]],operations[Month],'1'!$B$12) -> -2000 | J2: Other expences | N2: Expense
A3: Millennium | B3: Savings account | C3: 10.5 | D3: =SUMIFS(operations[Amount],operations[Bank],raports_6[[#This Row],[Bank]],operations[Product],raports_6[[#This Row],[Product]],operations[Month],$B$12) -> 0 | E3: =raports_6[[#This Row],[Opening balance]]+raports_6[[#This Row],[Operation]] -> 10.5 | G3: Clothing | H3: =SUMIFS(operations[Amount],operations[Category],Expenses5[[#This Row],[Category]],operations[Month],'1'!$B$12) -> -80 | J3: Studies | K3: =SUMIFS(operations[Amount],operations[Category],Table9162832[[#This Row],[Category]],operations[Month],'1'!$B$12) -> -100 | N3: Expense
A4: Santander | B4: Account | C4: 600 | D4: =SUMIFS(operations[Amount],operations[Bank],raports_6[[#This Row],[Bank]],operations[Product],raports_6[[#This Row],[Product]],operations[Month],$B$12) -> 2328.61 | E4: =raports_6[[#This Row],[Opening balance]]+raports_6[[#This Row],[Operation]] -> 2928.61 | G4: Entertainment | H4: =SUMIFS(operations[Amount],operations[Category],Expenses5[[#This Row],[Category]],operations[Month],'1'!$B$12) -> -85 | J4: Transportation | K4: =SUMIFS(operations[Amount],operations[Category],Table9162832[[#This Row],[Category]],operations[Month],'1'!$B$12) -> -80 | N4: Expense
A5: Santander | B5: Credit card | C5: 0 | D5: =SUMIFS(operations[Amount],operations[Bank],raports_6[[#This Row],[Bank]],operations[Product],raports_6[[#This Row],[Product]],operations[Month],$B$12) -> -908.61 | E5: =raports_6[[#This Row],[Opening balance]]+raports_6[[#This Row],[Operation]] -> -908.61 | G5: Groceries | H5: =SUMIFS(operations[Amount],operations[Category],Expenses5[[#This Row],[Category]],operations[Month],'1'!$B$12) -> -1715 | J5: Allowance | K5: =SUMIFS(operations[Amount],operations[Category],Table9162832[[#This Row],[Category]],operations[Month],'1'!$B$12) -> 250 | N5: Expense
A6: Santander | B6: Fixed-term deposit | C6: 2000 | D6: =SUMIFS(operations[Amount],operations[Bank],raports_6[[#This Row],[Bank]],operations[Product],raports_6[[#This Row],[Product]],operations[Month],$B$12) -> 0 | E6: =raports_6[[#This Row],[Opening balance]]+raports_6[[#This Row],[Operation]] -> 2000 | G6: Health&Beauty | H6: =SUMIFS(operations[Amount],operations[Category],Expenses5[[#This Row],[Category]],operations[Month],'1'!$B$12) -> -100 | J6: Financial | K6: =SUMIFS(operations[Amount],operations[Category],Table9162832[[#This Row],[Category]],operations[Month],'1'!$B$12) -> 105.5 | N6: Expense
A7: Wallet | B7: Gift card | C7: 200 | D7: =SUMIFS(operations[Amount],operations[Bank],raports_6[[#This Row],[Bank]],operations[Product],raports_6[[#This Row],[Product]],operations[Month],$B$12) -> 0 | E7: =raports_6[[#This Row],[Opening balance]]+raports_6[[#This Row],[Operation]] -> 200 | G7: Multimedia | H7: =SUMIFS(operations[Amount],operations[Category],Expenses5[[#This Row],[Category]],operations[Month],'1'!$B$12) -> -150 | J7: Gift | K7: =SUMIFS(operations[Amount],operations[Category],Table9162832[[#This Row],[Category]],operations[Month],'1'!$B$12) -> 0 | N7: Expense
A8: Wallet | B8: Money | C8: 30 | D8: =SUMIFS(operations[Amount],operations[Bank],raports_6[[#This Row],[Bank]],operations[Product],raports_6[[#This Row],[Product]],operations[Month],$B$12) -> -80 | E8: =raports_6[[#This Row],[Opening balance]]+raports_6[[#This Row],[Operation]] -> -50 | G8: Total | H8: =SUBTOTAL(109,Expenses5[Total]) -> -4130 | J8: Other incoms | K8: =SUMIFS(operations[Amount],operations[Category],Table9162832[[#This Row],[Category]],operations[Month],'1'!$B$12) -> 800 | N8: Expense
A9: Total | C9: =SUBTOTAL(109,raports_6[Opening balance]) -> #REF! | D9: =SUBTOTAL(109,raports_6[Operation]) -> 1290 | E9: =SUBTOTAL(109,raports_6[Closing balance]) -> #REF! | J9: Salary | K9: =SUMIFS(operations[Amount],operations[Category],Table9162832[[#This Row],[Category]],operations[Month],'1'!$B$12) -> 4500 | N9: Expense
J10: Scholarship | K10: =SUMIFS(operations[Amount],operations[Category],Table9162832[[#This Row],[Category]],operations[Month],'1'!$B$12) -> 0 | N10: Expense
J11: Transfer | K11: =SUMIFS(operations[Amount],operations[Category],Table9162832[[#This Row],[Category]],operations[Month],'1'!$B$12) -> 0 | N11: Income
A12: Month | B12: {=_xlfn.TEXTAFTER(CELL("filename",A1),"]")} -> 5 | J12: Total | K12: =SUBTOTAL(109,Table9162832[Total]) -> 5475.5 | N12: Income
N13: Income
A14: Type | B14: Total | N14: Income
A15: Income | B15: =SUMIFS(operations[Amount],operations[Type],balance_5[[#This Row],[Type]],operations[Month],'1'!$B$12) -> 5655.5 | N15: Income
A16: Expense | B16: =SUMIFS(operations[Amount],operations[Type],balance_5[[#This Row],[Type]],operations[Month],'1'!$B$12) -> -4810 | N16: Income
A17: Transfer | B17: =SUMIFS(operations[Amount],operations[Type],balance_5[[#This Row],[Type]],operations[Month],'1'!$B$12) -> 0 | N17: Transfer
A18: Total | B18: =SUBTOTAL(109,balance_5[Total]) -> 845.5

Sheet 3
A1: Bank | B1: Product | C1: Opening balance | D1: Operation | E1: Closing balance | G1: Category | H1: Total | J1: Category | K1: Total | N1: Type
A2: Millennium | B2: Account | C2: {=INDIRECT("raports_"&$B$12-1&"[@[Closing balance ]]")} -> #REF! | D2: =SUMIFS(operations[Amount],operations[Bank],raports_3[[#This Row],[Bank]],operations[Product],raports_3[[#This Row],[Product]],operations[Month],$B$12) -> 67.5 | E2: =raports_3[[#This Row],[Opening balance]]+raports_3[[#This Row],[Operation]] -> #REF! | G2: Accomodation | H2: =SUMIFS(operations[Amount],operations[Category],Expenses3[[#This Row],[Category]],operations[Month],'1'!$B$12) -> -2000 | J2: Other expences | N2: Expense
A3: Millennium | B3: Savings account | C3: 10.5 | D3: =SUMIFS(operations[Amount],operations[Bank],raports_3[[#This Row],[Bank]],operations[Product],raports_3[[#This Row],[Product]],operations[Month],$B$12) -> 5 | E3: =raports_3[[#This Row],[Opening balance]]+raports_3[[#This Row],[Operation]] -> 15.5 | G3: Clothing | H3: =SUMIFS(operations[Amount],operations[Category],Expenses3[[#This Row],[Category]],operations[Month],'1'!$B$12) -> -80 | J3: Studies | K3: =SUMIFS(operations[Amount],operations[Category],Table91624[[#This Row],[Category]],operations[Month],'1'!$B$12) -> -100 | N3: Expense
A4: Santander | B4: Account | C4: 600 | D4: =SUMIFS(operations[Amount],operations[Bank],raports_3[[#This Row],[Bank]],operations[Product],raports_3[[#This Row],[Product]],operations[Month],$B$12) -> 821.6 | E4: =raports_3[[#This Row],[Opening balance]]+raports_3[[#This Row],[Operation]] -> 1421.6 | G4: Entertainment | H4: =SUMIFS(operations[Amount],operations[Category],Expenses3[[#This Row],[Category]],operations[Month],'1'!$B$12) -> -85 | J4: Transportation | K4: =SUMIFS(operations[Amount],operations[Category],Table91624[[#This Row],[Category]],operations[Month],'1'!$B$12) -> -80 | N4: Expense
A5: Santander | B5: Credit card | C5: 0 | D5: =SUMIFS(operations[Amount],operations[Bank],raports_3[[#This Row],[Bank]],operations[Product],raports_3[[#This Row],[Product]],operations[Month],$B$12) -> -104.5 | E5: =raports_3[[#This Row],[Opening balance]]+raports_3[[#This Row],[Operation]] -> -104.5 | G5: Groceries | H5: =SUMIFS(operations[Amount],operations[Category],Expenses3[[#This Row],[Category]],operations[Month],'1'!$B$12) -> -1715 | J5: Allowance | K5: =SUMIFS(operations[Amount],operations[Category],Table91624[[#This Row],[Category]],operations[Month],'1'!$B$12) -> 250 | N5: Expense
A6: Santander | B6: Fixed-term deposit | C6: 2000 | D6: =SUMIFS(operations[Amount],operations[Bank],raports_3[[#This Row],[Bank]],operations[Product],raports_3[[#This Row],[Product]],operations[Month],$B$12) -> 0 | E6: =raports_3[[#This Row],[Opening balance]]+raports_3[[#This Row],[Operation]] -> 2000 | G6: Health&Beauty | H6: =SUMIFS(operations[Amount],operations[Category],Expenses3[[#This Row],[Category]],operations[Month],'1'!$B$12) -> -100 | J6: Financial | K6: =SUMIFS(operations[Amount],operations[Category],Table91624[[#This Row],[Category]],operations[Month],'1'!$B$12) -> 105.5 | N6: Expense
A7: Wallet | B7: Gift card | C7: 200 | D7: =SUMIFS(operations[Amount],operations[Bank],raports_3[[#This Row],[Bank]],operations[Product],raports_3[[#This Row],[Product]],operations[Month],$B$12) -> -24.49 | E7: =raports_3[[#This Row],[Opening balance]]+raports_3[[#This Row],[Operation]] -> 175.51 | G7: Multimedia | H7: =SUMIFS(operations[Amount],operations[Category],Expenses3[[#This Row],[Category]],operations[Month],'1'!$B$12) -> -150 | J7: Gift | K7: =SUMIFS(operations[Amount],operations[Category],Table91624[[#This Row],[Category]],operations[Month],'1'!$B$12) -> 0 | N7: Expense
A8: Wallet | B8: Money | C8: 30 | D8: =SUMIFS(operations[Amount],operations[Bank],raports_3[[#This Row],[Bank]],operations[Product],raports_3[[#This Row],[Product]],operations[Month],$B$12) -> -9.5 | E8: =raports_3[[#This Row],[Opening balance]]+raports_3[[#This Row],[Operation]] -> 20.5 | G8: Total | H8: =SUBTOTAL(109,Expenses3[Total]) -> -4130 | J8: Other incoms | K8: =SUMIFS(operations[Amount],operations[Category],Table91624[[#This Row],[Category]],operations[Month],'1'!$B$12) -> 800 | N8: Expense
A9: Total | C9: =SUBTOTAL(109,raports_3[Opening balance]) -> #REF! | D9: =SUBTOTAL(109,raports_3[Operation]) -> 755.61 | E9: =SUBTOTAL(109,raports_3[Closing balance]) -> #REF! | J9: Salary | K9: =SUMIFS(operations[Amount],operations[Category],Table91624[[#This Row],[Category]],operations[Month],'1'!$B$12) -> 4500 | N9: Expense
J10: Scholarship | K10: =SUMIFS(operations[Amount],operations[Category],Table91624[[#This Row],[Category]],operations[Month],'1'!$B$12) -> 0 | N10: Expense
J11: Transfer | K11: =SUMIFS(operations[Amount],operations[Category],Table91624[[#This Row],[Category]],operations[Month],'1'!$B$12) -> 0 | N11: Income
A12: Month | B12: {=_xlfn.TEXTAFTER(CELL("filename",A1),"]")} -> 3 | J12: Total | K12: =SUBTOTAL(109,Table91624[Total]) -> 5475.5 | N12: Income
N13: Income
A14: Type | B14: Total | N14: Income
A15: Income | B15: =SUMIFS(operations[Amount],operations[Type],balance_3[[#This Row],[Type]],operations[Month],'1'!$B$12) -> 5655.5 | N15: Income
A16: Expense | B16: =SUMIFS(operations[Amount],operations[Type],balance_3[[#This Row],[Type]],operations[Month],'1'!$B$12) -> -4810 | N16: Income
A17: Transfer | B17: =SUMIFS(operations[Amount],operations[Type],balance_3[[#This Row],[Type]],operations[Month],'1'!$B$12) -> 0 | N17: Transfer
A18: Total | B18: =SUBTOTAL(109,balance_3[Total]) -> 845.5

Sheet 2
A1: Bank | B1: Product | C1: Opening balance | D1: Operation | E1: Closing balance | G1: Category | H1: Total | J1: Category | K1: Total | N1: Type
A2: Millennium | B2: Account | C2: {=INDIRECT("raport_"&$B$12-1&"[@[Closing balance ]]")} -> #REF! | D2: =SUMIFS(operations[Amount],operations[Bank],raports_2[[#This Row],[Bank]],operations[Product],raports_2[[#This Row],[Product]],operations[Month],$B$12) -> 35 | E2: =raports_2[[#This Row],[Opening balance]]+raports_2[[#This Row],[Operation]] -> #REF! | G2: Accomodation | H2: =SUMIFS(operations[Amount],operations[Category],Expenses2[[#This Row],[Category]],operations[Month],'1'!$B$12) -> -2000 | J2: Other expences | N2: Expense
A3: Millennium | B3: Savings account | C3: 10.5 | D3: =SUMIFS(operations[Amount],operations[Bank],raports_2[[#This Row],[Bank]],operations[Product],raports_2[[#This Row],[Product]],operations[Month],$B$12) -> 15 | E3: =raports_2[[#This Row],[Opening balance]]+raports_2[[#This Row],[Operation]] -> 25.5 | G3: Clothing | H3: =SUMIFS(operations[Amount],operations[Category],Expenses2[[#This Row],[Category]],operations[Month],'1'!$B$12) -> -80 | J3: Studies | K3: =SUMIFS(operations[Amount],operations[Category],Table916[[#This Row],[Category]],operations[Month],'1'!$B$12) -> -100 | N3: Expense
A4: Santander | B4: Account | C4: 600 | D4: =SUMIFS(operations[Amount],operations[Bank],raports_2[[#This Row],[Bank]],operations[Product],raports_2[[#This Row],[Product]],operations[Month],$B$12) -> 2039.5 | E4: =raports_2[[#This Row],[Opening balance]]+raports_2[[#This Row],[Operation]] -> 2639.5 | G4: Entertainment | H4: =SUMIFS(operations[Amount],operations[Category],Expenses2[[#This Row],[Category]],operations[Month],'1'!$B$12) -> -85 | J4: Transportation | K4: =SUMIFS(operations[Amount],operations[Category],Table916[[#This Row],[Category]],operations[Month],'1'!$B$12) -> -80 | N4: Expense
A5: Santander | B5: Credit card | C5: 0 | D5: =SUMIFS(operations[Amount],operations[Bank],raports_2[[#This Row],[Bank]],operations[Product],raports_2[[#This Row],[Product]],operations[Month],$B$12) -> 175 | E5: =raports_2[[#This Row],[Opening balance]]+raports_2[[#This Row],[Operation]] -> 175 | G5: Groceries | H5: =SUMIFS(operations[Amount],operations[Category],Expenses2[[#This Row],[Category]],operations[Month],'1'!$B$12) -> -1715 | J5: Allowance | K5: =SUMIFS(operations[Amount],operations[Category],Table916[[#This Row],[Category]],operations[Month],'1'!$B$12) -> 250 | N5: Expense
A6: Santander | B6: Fixed-term deposit | C6: 2000 | D6: =SUMIFS(operations[Amount],operations[Bank],raports_2[[#This Row],[Bank]],operations[Product],raports_2[[#This Row],[Product]],operations[Month],$B$12) -> -400 | E6: =raports_2[[#This Row],[Opening balance]]+raports_2[[#This Row],[Operation]] -> 1600 | G6: Health&Beauty | H6: =SUMIFS(operations[Amount],operations[Category],Expenses2[[#This Row],[Category]],operations[Month],'1'!$B$12) -> -100 | J6: Financial | K6: =SUMIFS(operations[Amount],operations[Category],Table916[[#This Row],[Category]],operations[Month],'1'!$B$12) -> 105.5 | N6: Expense
A7: Wallet | B7: Gift card | C7: 200 | D7: =SUMIFS(operations[Amount],operations[Bank],raports_2[[#This Row],[Bank]],operations[Product],raports_2[[#This Row],[Product]],operations[Month],$B$12) -> 100 | E7: =raports_2[[#This Row],[Opening balance]]+raports_2[[#This Row],[Operation]] -> 300 | G7: Multimedia | H7: =SUMIFS(operations[Amount],operations[Category],Expenses2[[#This Row],[Category]],operations[Month],'1'!$B$12) -> -150 | J7: Gift | K7: =SUMIFS(operations[Amount],operations[Category],Table916[[#This Row],[Category]],operations[Month],'1'!$B$12) -> 0 | N7: Expense
A8: Wallet | B8: Money | C8: 30 | D8: =SUMIFS(operations[Amount],operations[Bank],raports_2[[#This Row],[Bank]],operations[Product],raports_2[[#This Row],[Product]],operations[Month],$B$12) -> 500 | E8: =raports_2[[#This Row],[Opening balance]]+raports_2[[#This Row],[Operation]] -> 530 | G8: Total | H8: =SUBTOTAL(109,Expenses2[Total]) -> -4130 | J8: Other incoms | K8: =SUMIFS(operations[Amount],operations[Category],Table916[[#This Row],[Category]],operations[Month],'1'!$B$12) -> 800 | N8: Expense
A9: Total | C9: =SUBTOTAL(109,raports_2[Opening balance]) -> #REF! | D9: =SUBTOTAL(109,raports_2[Operation]) -> 2464.5 | E9: =SUBTOTAL(109,raports_2[Closing balance]) -> #REF! | J9: Salary | K9: =SUMIFS(operations[Amount],operations[Category],Table916[[#This Row],[Category]],operations[Month],'1'!$B$12) -> 4500 | N9: Expense
J10: Scholarship | K10: =SUMIFS(operations[Amount],operations[Category],Table916[[#This Row],[Category]],operations[Month],'1'!$B$12) -> 0 | N10: Expense
J11: Transfer | K11: =SUMIFS(operations[Amount],operations[Category],Table916[[#This Row],[Category]],operations[Month],'1'!$B$12) -> 0 | N11: Income
A12: Month | B12: {=_xlfn.TEXTAFTER(CELL("filename",A1),"]")} -> 2 | J12: Total | K12: =SUBTOTAL(109,Table916[Total]) -> 5475.5 | N12: Income
N13: Income
A14: Type | B14: Total | N14: Income
A15: Income | B15: =SUMIFS(operations[Amount],operations[Type],balance_2[[#This Row],[Type]],operations[Month],'1'!$B$12) -> 5655.5 | N15: Income
A16: Expense | B16: =SUMIFS(operations[Amount],operations[Type],balance_2[[#This Row],[Type]],operations[Month],'1'!$B$12) -> -4810 | N16: Income
A17: Transfer | B17: =SUMIFS(operations[Amount],operations[Type],balance_2[[#This Row],[Type]],operations[Month],'1'!$B$12) -> 0 | N17: Transfer
A18: Total | B18: =SUBTOTAL(109,balance_2[Total]) -> 845.5

Sheet 1
A1: Bank | B1: Product | C1: Opening balance | D1: Operation | E1: Closing balance | G1: Category | H1: Total | J1: Category | K1: Total | N1: Type
A2: Millennium | B2: Account | C2: 100 | D2: =SUMIFS(operations[Amount],operations[Bank],raports_1[[#This Row],[Bank]],operations[Product],raports_1[[#This Row],[Product]],operations[Month],$B$12) -> -35 | E2: =raports_1[[#This Row],[Opening balance]]+raports_1[[#This Row],[Operation]] -> 65 | G2: Accomodation | H2: =SUMIFS(operations[Amount],operations[Category],Expenses[[#This Row],[Category]],operations[Month],'1'!$B$12) -> -2000 | J2: Other expences | K2: =SUMIFS(operations[Amount],operations[Category],Table9[[#This Row],[Category]],operations[Month],'1'!$B$12) -> -500 | N2: Expense
A3: Millennium | B3: Savings account | C3: 10.5 | D3: =SUMIFS(operations[Amount],operations[Bank],raports_1[[#This Row],[Bank]],operations[Product],raports_1[[#This Row],[Product]],operations[Month],$B$12) -> 255.5 | E3: =raports_1[[#This Row],[Opening balance]]+raports_1[[#This Row],[Operation]] -> 266 | G3: Clothing | H3: =SUMIFS(operations[Amount],operations[Category],Expenses[[#This Row],[Category]],operations[Month],'1'!$B$12) -> -80 | J3: Studies | K3: =SUMIFS(operations[Amount],operations[Category],Table9[[#This Row],[Category]],operations[Month],'1'!$B$12) -> -100 | N3: Expense
A4: Santander | B4: Account | C4: 600 | D4: =SUMIFS(operations[Amount],operations[Bank],raports_1[[#This Row],[Bank]],operations[Product],raports_1[[#This Row],[Product]],operations[Month],$B$12) -> 1100 | E4: =raports_1[[#This Row],[Opening balance]]+raports_1[[#This Row],[Operation]] -> 1700 | G4: Entertainment | H4: =SUMIFS(operations[Amount],operations[Category],Expenses[[#This Row],[Category]],operations[Month],'1'!$B$12) -> -85 | J4: Transportation | K4: =SUMIFS(operations[Amount],operations[Category],Table9[[#This Row],[Category]],operations[Month],'1'!$B$12) -> -80 | N4: Expense
A5: Santander | B5: Credit card | C5: 0 | D5: =SUMIFS(operations[Amount],operations[Bank],raports_1[[#This Row],[Bank]],operations[Product],raports_1[[#This Row],[Product]],operations[Month],$B$12) -> -175 | E5: =raports_1[[#This Row],[Opening balance]]+raports_1[[#This Row],[Operation]] -> -175 | G5: Groceries | H5: =SUMIFS(operations[Amount],operations[Category],Expenses[[#This Row],[Category]],operations[Month],'1'!$B$12) -> -1715 | J5: Allowance | K5: =SUMIFS(operations[Amount],operations[Category],Table9[[#This Row],[Category]],operations[Month],'1'!$B$12) -> 250 | N5: Expense
A6: Santander | B6: Fixed-term deposit | C6: 2000 | D6: =SUMIFS(operations[Amount],operations[Bank],raports_1[[#This Row],[Bank]],operations[Product],raports_1[[#This Row],[Product]],operations[Month],$B$12) -> -400 | E6: =raports_1[[#This Row],[Opening balance]]+raports_1[[#This Row],[Operation]] -> 1600 | G6: Health&Beauty | H6: =SUMIFS(operations[Amount],operations[Category],Expenses[[#This Row],[Category]],operations[Month],'1'!$B$12) -> -100 | J6: Financial | K6: =SUMIFS(operations[Amount],operations[Category],Table9[[#This Row],[Category]],operations[Month],'1'!$B$12) -> 105.5 | N6: Expense
A7: Wallet | B7: Gift card | C7: 200 | D7: =SUMIFS(operations[Amount],operations[Bank],raports_1[[#This Row],[Bank]],operations[Product],raports_1[[#This Row],[Product]],operations[Month],$B$12) -> -50 | E7: =raports_1[[#This Row],[Opening balance]]+raports_1[[#This Row],[Operation]] -> 150 | G7: Multimedia | H7: =SUMIFS(operations[Amount],operations[Category],Expenses[[#This Row],[Category]],operations[Month],'1'!$B$12) -> -150 | J7: Gift | K7: =SUMIFS(operations[Amount],operations[Category],Table9[[#This Row],[Category]],operations[Month],'1'!$B$12) -> 0 | N7: Expense
A8: Wallet | B8: Money | C8: 30 | D8: =SUMIFS(operations[Amount],operations[Bank],raports_1[[#This Row],[Bank]],operations[Product],raports_1[[#This Row],[Product]],operations[Month],$B$12) -> 150 | E8: =raports_1[[#This Row],[Opening balance]]+raports_1[[#This Row],[Operation]] -> 180 | G8: Total | H8: =SUBTOTAL(109,Expenses[Total]) -> -4130 | J8: Other incoms | K8: =SUMIFS(operations[Amount],operations[Category],Table9[[#This Row],[Category]],operations[Month],'1'!$B$12) -> 800 | N8: Expense
A9: Total | C9: =SUBTOTAL(109,raports_1[Opening balance]) -> 2940.5 | D9: =SUBTOTAL(109,raports_1[Operation]) -> 845.5 | E9: =SUBTOTAL(109,raports_1[Closing balance]) -> 3786 | J9: Salary | K9: =SUMIFS(operations[Amount],operations[Category],Table9[[#This Row],[Category]],operations[Month],'1'!$B$12) -> 4500 | N9: Expense
J10: Scholarship | K10: =SUMIFS(operations[Amount],operations[Category],Table9[[#This Row],[Category]],operations[Month],'1'!$B$12) -> 0 | N10: Expense
J11: Transfer | K11: =SUMIFS(operations[Amount],operations[Category],Table9[[#This Row],[Category]],operations[Month],'1'!$B$12) -> 0 | N11: Income
A12: Month | B12: {=_xlfn.TEXTAFTER(CELL("filename",A1),"]")} -> 1 | J12: Total | K12: =SUBTOTAL(109,Table9[Total]) -> 4975.5 | N12: Income
N13: Income
A14: Type | B14: Total | N14: Income
A15: Income | B15: =SUMIFS(operations[Amount],operations[Type],balance_1[[#This Row],[Type]],operations[Month],'1'!$B$12) -> 5655.5 | N15: Income
A16: Expense | B16: =SUMIFS(operations[Amount],operations[Type],balance_1[[#This Row],[Type]],operations[Month],'1'!$B$12) -> -4810 | N16: Income
A17: Transfer | B17: =SUMIFS(operations[Amount],operations[Type],balance_1[[#This Row],[Type]],operations[Month],'1'!$B$12) -> 0 | N17: Transfer
A18: Total | B18: =SUBTOTAL(109,balance_1[Total]) -> 845.5

Sheet 4
A1: Bank | B1: Product | C1: Opening balance | D1: Operation | E1: Closing balance | G1: Category | H1: Total | J1: Category | K1: Total | N1: Type
A2: Millennium | B2: Account | C2: {=INDIRECT("raport_"&$B$12-1&"[@[Closing balance ]]")} -> #REF! | D2: =SUMIFS(operations[Amount],operations[Bank],raports_4[[#This Row],[Bank]],operations[Product],raports_4[[#This Row],[Product]],operations[Month],$B$12) -> 101 | E2: =raports_4[[#This Row],[Opening balance]]+raports_4[[#This Row],[Operation]] -> #REF! | G2: Accomodation | H2: =SUMIFS(operations[Amount],operations[Category],Expenses4[[#This Row],[Category]],operations[Month],'1'!$B$12) -> -2000 | J2: Other expences | N2: Expense
A3: Millennium | B3: Savings account | C3: 10.5 | D3: =SUMIFS(operations[Amount],operations[Bank],raports_4[[#This Row],[Bank]],operations[Product],raports_4[[#This Row],[Product]],operations[Month],$B$12) -> 50 | E3: =raports_4[[#This Row],[Opening balance]]+raports_4[[#This Row],[Operation]] -> 60.5 | G3: Clothing | H3: =SUMIFS(operations[Amount],operations[Category],Expenses4[[#This Row],[Category]],operations[Month],'1'!$B$12) -> -80 | J3: Studies | K3: =SUMIFS(operations[Amount],operations[Category],Table91628[[#This Row],[Category]],operations[Month],'1'!$B$12) -> -100 | N3: Expense
A4: Santander | B4: Account | C4: 600 | D4: =SUMIFS(operations[Amount],operations[Bank],raports_4[[#This Row],[Bank]],operations[Product],raports_4[[#This Row],[Product]],operations[Month],$B$12) -> 562.73 | E4: =raports_4[[#This Row],[Opening balance]]+raports_4[[#This Row],[Operation]] -> 1162.73 | G4: Entertainment | H4: =SUMIFS(operations[Amount],operations[Category],Expenses4[[#This Row],[Category]],operations[Month],'1'!$B$12) -> -85 | J4: Transportation | K4: =SUMIFS(operations[Amount],operations[Category],Table91628[[#This Row],[Category]],operations[Month],'1'!$B$12) -> -80 | N4: Expense
A5: Santander | B5: Credit card | C5: 0 | D5: =SUMIFS(operations[Amount],operations[Bank],raports_4[[#This Row],[Bank]],operations[Product],raports_4[[#This Row],[Product]],operations[Month],$B$12) -> 13.11 | E5: =raports_4[[#This Row],[Opening balance]]+raports_4[[#This Row],[Operation]] -> 13.11 | G5: Groceries | H5: =SUMIFS(operations[Amount],operations[Category],Expenses4[[#This Row],[Category]],operations[Month],'1'!$B$12) -> -1715 | J5: Allowance | K5: =SUMIFS(operations[Amount],operations[Category],Table91628[[#This Row],[Category]],operations[Month],'1'!$B$12) -> 250 | N5: Expense
A6: Santander | B6: Fixed-term deposit | C6: 2000 | D6: =SUMIFS(operations[Amount],operations[Bank],raports_4[[#This Row],[Bank]],operations[Product],raports_4[[#This Row],[Product]],operations[Month],$B$12) -> 0 | E6: =raports_4[[#This Row],[Opening balance]]+raports_4[[#This Row],[Operation]] -> 2000 | G6: Health&Beauty | H6: =SUMIFS(operations[Amount],operations[Category],Expenses4[[#This Row],[Category]],operations[Month],'1'!$B$12) -> -100 | J6: Financial | K6: =SUMIFS(operations[Amount],operations[Category],Table91628[[#This Row],[Category]],operations[Month],'1'!$B$12) -> 105.5 | N6: Expense
A7: Wallet | B7: Gift card | C7: 200 | D7: =SUMIFS(operations[Amount],operations[Bank],raports_4[[#This Row],[Bank]],operations[Product],raports_4[[#This Row],[Product]],operations[Month],$B$12) -> 0 | E7: =raports_4[[#This Row],[Opening balance]]+raports_4[[#This Row],[Operation]] -> 200 | G7: Multimedia | H7: =SUMIFS(operations[Amount],operations[Category],Expenses4[[#This Row],[Category]],operations[Month],'1'!$B$12) -> -150 | J7: Gift | K7: =SUMIFS(operations[Amount],operations[Category],Table91628[[#This Row],[Category]],operations[Month],'1'!$B$12) -> 0 | N7: Expense
A8: Wallet | B8: Money | C8: 30 | D8: =SUMIFS(operations[Amount],operations[Bank],raports_4[[#This Row],[Bank]],operations[Product],raports_4[[#This Row],[Product]],operations[Month],$B$12) -> 0 | E8: =raports_4[[#This Row],[Opening balance]]+raports_4[[#This Row],[Operation]] -> 30 | G8: Total | H8: =SUBTOTAL(109,Expenses4[Total]) -> -4130 | J8: Other incoms | K8: =SUMIFS(operations[Amount],operations[Category],Table91628[[#This Row],[Category]],operations[Month],'1'!$B$12) -> 800 | N8: Expense
A9: Total | C9: =SUBTOTAL(109,raports_4[Opening balance]) -> #REF! | D9: =SUBTOTAL(109,raports_4[Operation]) -> 726.84 | E9: =SUBTOTAL(109,raports_4[Closing balance]) -> #REF! | J9: Salary | K9: =SUMIFS(operations[Amount],operations[Category],Table91628[[#This Row],[Category]],operations[Month],'1'!$B$12) -> 4500 | N9: Expense
J10: Scholarship | K10: =SUMIFS(operations[Amount],operations[Category],Table91628[[#This Row],[Category]],operations[Month],'1'!$B$12) -> 0 | N10: Expense
J11: Transfer | K11: =SUMIFS(operations[Amount],operations[Category],Table91628[[#This Row],[Category]],operations[Month],'1'!$B$12) -> 0 | N11: Income
A12: Month | B12: {=_xlfn.TEXTAFTER(CELL("filename",A1),"]")} -> 4 | J12: Total | K12: =SUBTOTAL(109,Table91628[Total]) -> 5475.5 | N12: Income
N13: Income
A14: Type | B14: Total | N14: Income
A15: Income | B15: =SUMIFS(operations[Amount],operations[Type],balance_4[[#This Row],[Type]],operations[Month],'1'!$B$12) -> 5655.5 | N15: Income
A16: Expense | B16: =SUMIFS(operations[Amount],operations[Type],balance_4[[#This Row],[Type]],operations[Month],'1'!$B$12) -> -4810 | N16: Income
A17: Transfer | B17: =SUMIFS(operations[Amount],operations[Type],balance_4[[#This Row],[Type]],operations[Month],'1'!$B$12) -> 0 | N17: Transfer
A18: Total | B18: =SUBTOTAL(109,balance_4[Total]) -> 845.5

Sheet dictionary
A1: Category | B1: Type | D1: Bank | E1: Product | H1: Millennium | I1: Santander | J1: Wallet
A2: Accomodation | B2: Expense | D2: Millennium | E2: Account | H2: Account | I2: Account | J2: Gift card
A3: Clothing | B3: Expense | D3: Millennium | E3: Savings account | H3: Savings account | I3: Credit card | J3: Money
A4: Entertainment | B4: Expense | D4: Santander | E4: Account | I4: Fixed-term deposit
A5: Groceries | B5: Expense | D5: Santander | E5: Credit card
A6: Health&Beauty | B6: Expense | D6: Santander | E6: Fixed-term deposit
A7: Multimedia | B7: Expense | D7: Wallet | E7: Gift card
A8: Other expences | B8: Expense | D8: Wallet | E8: Money
A9: Studies | B9: Expense
A10: Transportation | B10: Expense
A11: Allowance | B11: Income
A12: Financial | B12: Income
A13: Gift | B13: Income
A14: Other incoms | B14: Income
A15: Salary | B15: Income
A16: Scholarship | B16: Income
A17: Transfer | B17: Transfer

Sheet operations
A1: Amount | B1: Bank | C1: Product | D1: Category | E1: Type | F1: Date | G1: Month
A2: -1500 | B2: Santander | C2: Account | D2: Groceries | E2: =_xlfn.XLOOKUP(operations[[#This Row],[Category]],categories[Category],categories[Type],"",0,1) -> Expense | F2: 45296 | G2: =MONTH(operations[[#This Row],[Date]]) -> 1 | J2: {=CHOOSE(MATCH(B2,dictionary!$H$1:$J$1,0),_xlfn._TRO_TRAILING(dictionary!$H$2:$H$8),_xlfn._TRO_TRAILING(dictionary!$I$2:$I$8),_xlfn._TRO_TRAILING(dictionary!$J$2:$J$8))} -> Account
A3: 4500 | B3: Santander | C3: Account | D3: Salary | E3: =_xlfn.XLOOKUP(operations[[#This Row],[Category]],categories[Category],categories[Type],"",0,1) -> Income | F3: 45301 | G3: =MONTH(operations[[#This Row],[Date]]) -> 1 | J3: Credit card
A4: -2000 | B4: Santander | C4: Account | D4: Accomodation | E4: =_xlfn.XLOOKUP(operations[[#This Row],[Category]],categories[Category],categories[Type],"",0,1) -> Expense | F4: 45302 | G4: =MONTH(operations[[#This Row],[Date]]) -> 1 | J4: Fixed-term deposit
A5: -45 | B5: Millennium | C5: Account | D5: Groceries | E5: =_xlfn.XLOOKUP(operations[[#This Row],[Category]],categories[Category],categories[Type],"",0,1) -> Expense | F5: 45305 | G5: =MONTH(operations[[#This Row],[Date]]) -> 1
A6: -150 | B6: Santander | C6: Credit card | D6: Multimedia | E6: =_xlfn.XLOOKUP(operations[[#This Row],[Category]],categories[Category],categories[Type],"",0,1) -> Expense | F6: 45306 | G6: =MONTH(operations[[#This Row],[Date]]) -> 1
A7: -120 | B7: Santander | C7: Account | D7: Groceries | E7: =_xlfn.XLOOKUP(operations[[#This Row],[Category]],categories[Category],categories[Type],"",0,1) -> Expense | F7: 45307 | G7: =MONTH(operations[[#This Row],[Date]]) -> 1 | P7: {=CHOOSE(MATCH(B2,dictionary!$H$1:$J$1,0),_xlfn._TRO_TRAILING(dictionary!$H$2:$H$8),_xlfn._TRO_TRAILING(dictionary!$I$2:$I$8),_xlfn._TRO_TRAILING(dictionary!$J$2:$J$8))} -> Account
A8: 500 | B8: Santander | C8: Account | D8: Other incoms | E8: =_xlfn.XLOOKUP(operations[[#This Row],[Category]],categories[Category],categories[Type],"",0,1) -> Income | F8: 45308 | G8: =MONTH(operations[[#This Row],[Date]]) -> 1 | P8: Credit card
A9: -500 | B9: Santander | C9: Fixed-term deposit | D9: Other expences | E9: =_xlfn.XLOOKUP(operations[[#This Row],[Category]],categories[Category],categories[Type],"",0,1) -> Expense | F9: 45308 | G9: =MONTH(operations[[#This Row],[Date]]) -> 1 | P9: Fixed-term deposit
A10: 250 | B10: Millennium | C10: Savings account | D10: Allowance | E10: =_xlfn.XLOOKUP(operations[[#This Row],[Category]],categories[Category],categories[Type],"",0,1) -> Income | F10: 45308 | G10: =MONTH(operations[[#This Row],[Date]]) -> 1
A11: -25 | B11: Santander | C11: Credit card | D11: Entertainment | E11: =_xlfn.XLOOKUP(operations[[#This Row],[Category]],categories[Category],categories[Type],"",0,1) -> Expense | F11: 45310 | G11: =MONTH(operations[[#This Row],[Date]]) -> 1
A12: -80 | B12: Santander | C12: Account | D12: Transportation | E12: =_xlfn.XLOOKUP(operations[[#This Row],[Category]],categories[Category],categories[Type],"",0,1) -> Expense | F12: 45311 | G12: =MONTH(operations[[#This Row],[Date]]) -> 1
A13: 150 | B13: Millennium | C13: Account | D13: Other incoms | E13: =_xlfn.XLOOKUP(operations[[#This Row],[Category]],categories[Category],categories[Type],"",0,1) -> Income | F13: 45312 | G13: =MONTH(operations[[#This Row],[Date]]) -> 1
A14: -80 | B14: Millennium | C14: Account | D14: Clothing | E14: =_xlfn.XLOOKUP(operations[[#This Row],[Category]],categories[Category],categories[Type],"",0,1) -> Expense | F14: 45313 | G14: =MONTH(operations[[#This Row],[Date]]) -> 1
A15: -60 | B15: Millennium | C15: Account | D15: Entertainment | E15: =_xlfn.XLOOKUP(operations[[#This Row],[Category]],categories[Category],categories[Type],"",0,1) -> Expense | F15: 45314 | G15: =MONTH(operations[[#This Row],[Date]]) -> 1
A16: -100 | B16: Santander | C16: Account | D16: Studies | E16: =_xlfn.XLOOKUP(operations[[#This Row],[Category]],categories[Category],categories[Type],"",0,1) -> Expense | F16: 45315 | G16: =MONTH(operations[[#This Row],[Date]]) -> 1
A17: -50 | B17: Wallet | C17: Gift card | D17: Groceries | E17: =_xlfn.XLOOKUP(operations[[#This Row],[Category]],categories[Category],categories[Type],"",0,1) -> Expense | F17: 45316 | G17: =MONTH(operations[[#This Row],[Date]]) -> 1
A18: 150 | B18: Wallet | C18: Money | D18: Other incoms | E18: =_xlfn.XLOOKUP(operations[[#This Row],[Category]],categories[Category],categories[Type],"",0,1) -> Income | F18: 45316 | G18: =MONTH(operations[[#This Row],[Date]]) -> 1
A19: 5.5 | B19: Millennium | C19: Savings account | D19: Financial | E19: =_xlfn.XLOOKUP(operations[[#This Row],[Category]],categories[Category],categories[Type],"",0,1) -> Income | F19: 45317 | G19: =MONTH(operations[[#This Row],[Date]]) -> 1
A20: 100 | B20: Santander | C20: Fixed-term deposit | D20: Financial | E20: =_xlfn.XLOOKUP(operations[[#This Row],[Category]],categories[Category],categories[Type],"",0,1) -> Income | F20: 45318 | G20: =MONTH(operations[[#This Row],[Date]]) -> 1
A21: -100 | B21: Santander | C21: Account | D21: Health&Beauty | E21: =_xlfn.XLOOKUP(operations[[#This Row],[Category]],categories[Category],categories[Type],"",0,1) -> Expense | F21: 45319 | G21: =MONTH(operations[[#This Row],[Date]]) -> 1
... A207: -300 | B207: Wallet | C207: Money | D207: Groceries | E207: =_xlfn.XLOOKUP(operations[[#This Row],[Category]],categories[Category],categories[Type],"",0,1) -> Expense | F207: 45656 | G207: =MONTH(operations[[#This Row],[Date]]) -> 12

Sheet summary1
A1: Category | B1: Type | C1: 1 | D1: 2 | E1: 3 | F1: 4 | G1: 5 | H1: 6 | I1: 7 | J1: 8 | K1: 9 | L1: 10 | M1: 11 | N1: 12
A2: Accomodation | B2: Expense | C2: {=SUMIFS(operations[[Amount]:[Amount]],operations[[Category]:[Category]],summary1[[#This Row],[Category]:[Category]],operations[[Month]:[Month]],summary1[[#Headers],[1]])} -> -2000 | D2: {=SUMIFS(operations[[Amount]:[Amount]],operations[[Category]:[Category]],summary1[[#This Row],[Category]:[Category]],operations[[Month]:[Month]],summary1[[#Headers],[2]])} -> -2000 | E2: {=SUMIFS(operations[[Amount]:[Amount]],operations[[Category]:[Category]],summary1[[#This Row],[Category]:[Category]],operations[[Month]:[Month]],summary1[[#Headers],[3]])} -> -2000 | F2: {=SUMIFS(operations[[Amount]:[Amount]],operations[[Category]:[Category]],summary1[[#This Row],[Category]:[Category]],operations[[Month]:[Month]],summary1[[#Headers],[4]])} -> -2000 | G2: {=SUMIFS(operations[[Amount]:[Amount]],operations[[Category]:[Category]],summary1[[#This Row],[Category]:[Category]],operations[[Month]:[Month]],summary1[[#Headers],[5]])} -> -2000 | H2: {=SUMIFS(operations[[Amount]:[Amount]],operations[[Category]:[Category]],summary1[[#This Row],[Category]:[Category]],operations[[Month]:[Month]],summary1[[#Headers],[6]])} -> -2000 | I2: {=SUMIFS(operations[[Amount]:[Amount]],operations[[Category]:[Category]],summary1[[#This Row],[Category]:[Category]],operations[[Month]:[Month]],summary1[[#Headers],[7]])} -> -2000 | J2: {=SUMIFS(operations[[Amount]:[Amount]],operations[[Category]:[Category]],summary1[[#This Row],[Category]:[Category]],operations[[Month]:[Month]],summary1[[#Headers],[8]])} -> -2000 | K2: {=SUMIFS(operations[[Amount]:[Amount]],operations[[Category]:[Category]],summary1[[#This Row],[Category]:[Category]],operations[[Month]:[Month]],summary1[[#Headers],[9]])} -> -2000 | L2: {=SUMIFS(operations[[Amount]:[Amount]],operations[[Category]:[Category]],summary1[[#This Row],[Category]:[Category]],operations[[Month]:[Month]],summary1[[#Headers],[10]])} -> -2000 | M2: {=SUMIFS(operations[[Amount]:[Amount]],operations[[Category]:[Category]],summary1[[#This Row],[Category]:[Category]],operations[[Month]:[Month]],summary1[[#Headers],[11]])} -> -2000 | N2: {=SUMIFS(operations[[Amount]:[Amount]],operations[[Category]:[Category]],summary1[[#This Row],[Category]:[Category]],operations[[Month]:[Month]],summary1[[#Headers],[12]])} -> -2000
A3: Clothing | B3: Expense | C3: {=SUMIFS(operations[[Amount]:[Amount]],operations[[Category]:[Category]],summary1[[#This Row],[Category]:[Category]],operations[[Month]:[Month]],summary1[[#Headers],[1]])} -> -80 | D3: {=SUMIFS(operations[[Amount]:[Amount]],operations[[Category]:[Category]],summary1[[#This Row],[Category]:[Category]],operations[[Month]:[Month]],summary1[[#Headers],[2]])} -> 0 | E3: {=SUMIFS(operations[[Amount]:[Amount]],operations[[Category]:[Category]],summary1[[#This Row],[Category]:[Category]],operations[[Month]:[Month]],summary1[[#Headers],[3]])} -> -469.9 | F3: {=SUMIFS(operations[[Amount]:[Amount]],operations[[Category]:[Category]],summary1[[#This Row],[Category]:[Category]],operations[[Month]:[Month]],summary1[[#Headers],[4]])} -> -149 | G3: {=SUMIFS(operations[[Amount]:[Amount]],operations[[Category]:[Category]],summary1[[#This Row],[Category]:[Category]],operations[[Month]:[Month]],summary1[[#Headers],[5]])} -> 0 | H3: {=SUMIFS(operations[[Amount]:[Amount]],operations[[Category]:[Category]],summary1[[#This Row],[Category]:[Category]],operations[[Month]:[Month]],summary1[[#Headers],[6]])} -> -300 | I3: {=SUMIFS(operations[[Amount]:[Amount]],operations[[Category]:[Category]],summary1[[#This Row],[Category]:[Category]],operations[[Month]:[Month]],summary1[[#Headers],[7]])} -> 250 | J3: {=SUMIFS(operations[[Amount]:[Amount]],operations[[Category]:[Category]],summary1[[#This Row],[Category]:[Category]],operations[[Month]:[Month]],summary1[[#Headers],[8]])} -> -300 | K3: {=SUMIFS(operations[[Amount]:[Amount]],operations[[Category]:[Category]],summary1[[#This Row],[Category]:[Category]],operations[[Month]:[Month]],summary1[[#Headers],[9]])} -> 0 | L3: {=SUMIFS(operations[[Amount]:[Amount]],operations[[Category]:[Category]],summary1[[#This Row],[Category]:[Category]],operations[[Month]:[Month]],summary1[[#Headers],[10]])} -> 0 | M3: {=SUMIFS(operations[[Amount]:[Amount]],operations[[Category]:[Category]],summary1[[#This Row],[Category]:[Category]],operations[[Month]:[Month]],summary1[[#Headers],[11]])} -> -158 | N3: {=SUMIFS(operations[[Amount]:[Amount]],operations[[Category]:[Category]],summary1[[#This Row],[Category]:[Category]],operations[[Month]:[Month]],summary1[[#Headers],[12]])} -> -120
A4: Entertainment | B4: Expense | C4: {=SUMIFS(operations[[Amount]:[Amount]],operations[[Category]:[Category]],summary1[[#This Row],[Category]:[Category]],operations[[Month]:[Month]],summary1[[#Headers],[1]])} -> -85 | D4: {=SUMIFS(operations[[Amount]:[Amount]],operations[[Category]:[Category]],summary1[[#This Row],[Category]:[Category]],operations[[Month]:[Month]],summary1[[#Headers],[2]])} -> -350 | E4: {=SUMIFS(operations[[Amount]:[Amount]],operations[[Category]:[Category]],summary1[[#This Row],[Category]:[Category]],operations[[Month]:[Month]],summary1[[#Headers],[3]])} -> -200 | F4: {=SUMIFS(operations[[Amount]:[Amount]],operations[[Category]:[Category]],summary1[[#This Row],[Category]:[Category]],operations[[Month]:[Month]],summary1[[#Headers],[4]])} -> -1057.9 | G4: {=SUMIFS(operations[[Amount]:[Amount]],operations[[Category]:[Category]],summary1[[#This Row],[Category]:[Category]],operations[[Month]:[Month]],summary1[[#Headers],[5]])} -> -80 | H4: {=SUMIFS(operations[[Amount]:[Amount]],operations[[Category]:[Category]],summary1[[#This Row],[Category]:[Category]],operations[[Month]:[Month]],summary1[[#Headers],[6]])} -> -200 | I4: {=SUMIFS(operations[[Amount]:[Amount]],operations[[Category]:[Category]],summary1[[#This Row],[Category]:[Category]],operations[[Month]:[Month]],summary1[[#Headers],[7]])} -> -700 | J4: {=SUMIFS(operations[[Amount]:[Amount]],operations[[Category]:[Category]],summary1[[#This Row],[Category]:[Category]],operations[[Month]:[Month]],summary1[[#Headers],[8]])} -> -250 | K4: {=SUMIFS(operations[[Amount]:[Amount]],operations[[Category]:[Category]],summary1[[#This Row],[Category]:[Category]],operations[[Month]:[Month]],summary1[[#Headers],[9]])} -> -20 | L4: {=SUMIFS(operations[[Amount]:[Amount]],operations[[Category]:[Category]],summary1[[#This Row],[Category]:[Category]],operations[[Month]:[Month]],summary1[[#Headers],[10]])} -> -40 | M4: {=SUMIFS(operations[[Amount]:[Amount]],operations[[Category]:[Category]],summary1[[#This Row],[Category]:[Category]],operations[[Month]:[Month]],summary1[[#Headers],[11]])} -> -214 | N4: {=SUMIFS(operations[[Amount]:[Amount]],operations[[Category]:[Category]],summary1[[#This Row],[Category]:[Category]],operations[[Month]:[Month]],summary1[[#Headers],[12]])} -> -450
A5: Groceries | B5: Expense | C5: {=SUMIFS(operations[[Amount]:[Amount]],operations[[Category]:[Category]],summary1[[#This Row],[Category]:[Category]],operations[[Month]:[Month]],summary1[[#Headers],[1]])} -> -1715 | D5: {=SUMIFS(operations[[Amount]:[Amount]],operations[[Category]:[Category]],summary1[[#This Row],[Category]:[Category]],operations[[Month]:[Month]],summary1[[#Headers],[2]])} -> -405.5 | E5: {=SUMIFS(operations[[Amount]:[Amount]],operations[[Category]:[Category]],summary1[[#This Row],[Category]:[Category]],operations[[Month]:[Month]],summary1[[#Headers],[3]])} -> -734.99 | F5: {=SUMIFS(operations[[Amount]:[Amount]],operations[[Category]:[Category]],summary1[[#This Row],[Category]:[Category]],operations[[Month]:[Month]],summary1[[#Headers],[4]])} -> -372.26 | G5: {=SUMIFS(operations[[Amount]:[Amount]],operations[[Category]:[Category]],summary1[[#This Row],[Category]:[Category]],operations[[Month]:[Month]],summary1[[#Headers],[5]])} -> -1000 | H5: {=SUMIFS(operations[[Amount]:[Amount]],operations[[Category]:[Category]],summary1[[#This Row],[Category]:[Category]],operations[[Month]:[Month]],summary1[[#Headers],[6]])} -> -1000 | I5: {=SUMIFS(operations[[Amount]:[Amount]],operations[[Category]:[Category]],summary1[[#This Row],[Category]:[Category]],operations[[Month]:[Month]],summary1[[#Headers],[7]])} -> -165 | J5: {=SUMIFS(operations[[Amount]:[Amount]],operations[[Category]:[Category]],summary1[[#This Row],[Category]:[Category]],operations[[Month]:[Month]],summary1[[#Headers],[8]])} -> -749.5 | K5: {=SUMIFS(operations[[Amount]:[Amount]],operations[[Category]:[Category]],summary1[[#This Row],[Category]:[Category]],operations[[Month]:[Month]],summary1[[#Headers],[9]])} -> -538.5 | L5: {=SUMIFS(operations[[Amount]:[Amount]],operations[[Category]:[Category]],summary1[[#This Row],[Category]:[Category]],operations[[Month]:[Month]],summary1[[#Headers],[10]])} -> -600 | M5: {=SUMIFS(operations[[Amount]:[Amount]],operations[[Category]:[Category]],summary1[[#This Row],[Category]:[Category]],operations[[Month]:[Month]],summary1[[#Headers],[11]])} -> -506 | N5: {=SUMIFS(operations[[Amount]:[Amount]],operations[[Category]:[Category]],summary1[[#This Row],[Category]:[Category]],operations[[Month]:[Month]],summary1[[#Headers],[12]])} -> -700
A6: Health&Beauty | B6: Expense | C6: {=SUMIFS(operations[[Amount]:[Amount]],operations[[Category]:[Category]],summary1[[#This Row],[Category]:[Category]],operations[[Month]:[Month]],summary1[[#Headers],[1]])} -> -100 | D6: {=SUMIFS(operations[[Amount]:[Amount]],operations[[Category]:[Category]],summary1[[#This Row],[Category]:[Category]],operations[[Month]:[Month]],summary1[[#Headers],[2]])} -> -250 | E6: {=SUMIFS(operations[[Amount]:[Amount]],operations[[Category]:[Category]],summary1[[#This Row],[Category]:[Category]],operations[[Month]:[Month]],summary1[[#Headers],[3]])} -> -9.5 | F6: {=SUMIFS(operations[[Amount]:[Amount]],operations[[Category]:[Category]],summary1[[#This Row],[Category]:[Category]],operations[[Month]:[Month]],summary1[[#Headers],[4]])} -> -23.5 | G6: {=SUMIFS(operations[[Amount]:[Amount]],operations[[Category]:[Category]],summary1[[#This Row],[Category]:[Category]],operations[[Month]:[Month]],summary1[[#Headers],[5]])} -> 0 | H6: {=SUMIFS(operations[[Amount]:[Amount]],operations[[Category]:[Category]],summary1[[#This Row],[Category]:[Category]],operations[[Month]:[Month]],summary1[[#Headers],[6]])} -> -100 | I6: {=SUMIFS(operations[[Amount]:[Amount]],operations[[Category]:[Category]],summary1[[#This Row],[Category]:[Category]],operations[[Month]:[Month]],summary1[[#Headers],[7]])} -> -300 | J6: {=SUMIFS(operations[[Amount]:[Amount]],operations[[Category]:[Category]],summary1[[#This Row],[Category]:[Category]],operations[[Month]:[Month]],summary1[[#Headers],[8]])} -> -400 | K6: {=SUMIFS(operations[[Amount]:[Amount]],operations[[Category]:[Category]],summary1[[#This Row],[Category]:[Category]],operations[[Month]:[Month]],summary1[[#Headers],[9]])} -> 0 | L6: {=SUMIFS(operations[[Amount]:[Amount]],operations[[Category]:[Category]],summary1[[#This Row],[Category]:[Category]],operations[[Month]:[Month]],summary1[[#Headers],[10]])} -> 0 | M6: {=SUMIFS(operations[[Amount]:[Amount]],operations[[Category]:[Category]],summary1[[#This Row],[Category]:[Category]],operations[[Month]:[Month]],summary1[[#Headers],[11]])} -> -133 | N6: {=SUMIFS(operations[[Amount]:[Amount]],operations[[Category]:[Category]],summary1[[#This Row],[Category]:[Category]],operations[[Month]:[Month]],summary1[[#Headers],[12]])} -> -10
A7: Multimedia | B7: Expense | C7: {=SUMIFS(operations[[Amount]:[Amount]],operations[[Category]:[Category]],summary1[[#This Row],[Category]:[Category]],operations[[Month]:[Month]],summary1[[#Headers],[1]])} -> -150 | D7: {=SUMIFS(operations[[Amount]:[Amount]],operations[[Category]:[Category]],summary1[[#This Row],[Category]:[Category]],operations[[Month]:[Month]],summary1[[#Headers],[2]])} -> -150 | E7: {=SUMIFS(operations[[Amount]:[Amount]],operations[[Category]:[Category]],summary1[[#This Row],[Category]:[Category]],operations[[Month]:[Month]],summary1[[#Headers],[3]])} -> -23 | F7: {=SUMIFS(operations[[Amount]:[Amount]],operations[[Category]:[Category]],summary1[[#This Row],[Category]:[Category]],operations[[Month]:[Month]],summary1[[#Headers],[4]])} -> -49 | G7: {=SUMIFS(operations[[Amount]:[Amount]],operations[[Category]:[Category]],summary1[[#This Row],[Category]:[Category]],operations[[Month]:[Month]],summary1[[#Headers],[5]])} -> -50 | H7: {=SUMIFS(operations[[Amount]:[Amount]],operations[[Category]:[Category]],summary1[[#This Row],[Category]:[Category]],operations[[Month]:[Month]],summary1[[#Headers],[6]])} -> -50 | I7: {=SUMIFS(operations[[Amount]:[Amount]],operations[[Category]:[Category]],summary1[[#This Row],[Category]:[Category]],operations[[Month]:[Month]],summary1[[#Headers],[7]])} -> 0 | J7: {=SUMIFS(operations[[Amount]:[Amount]],operations[[Category]:[Category]],summary1[[#This Row],[Category]:[Category]],operations[[Month]:[Month]],summary1[[#Headers],[8]])} -> 0 | K7: {=SUMIFS(operations[[Amount]:[Amount]],operations[[Category]:[Category]],summary1[[#This Row],[Category]:[Category]],operations[[Month]:[Month]],summary1[[#Headers],[9]])} -> -40 | L7: {=SUMIFS(operations[[Amount]:[Amount]],operations[[Category]:[Category]],summary1[[#This Row],[Category]:[Category]],operations[[Month]:[Month]],summary1[[#Headers],[10]])} -> -40 | M7: {=SUMIFS(operations[[Amount]:[Amount]],operations[[Category]:[Category]],summary1[[#This Row],[Category]:[Category]],operations[[Month]:[Month]],summary1[[#Headers],[11]])} -> -47 | N7: {=SUMIFS(operations[[Amount]:[Amount]],operations[[Category]:[Category]],summary1[[#This Row],[Category]:[Category]],operations[[Month]:[Month]],summary1[[#Headers],[12]])} -> 0
A8: Other expences | B8: Expense | C8: {=SUMIFS(operations[[Amount]:[Amount]],operations[[Category]:[Category]],summary1[[#This Row],[Category]:[Category]],operations[[Month]:[Month]],summary1[[#Headers],[1]])} -> -500 | D8: {=SUMIFS(operations[[Amount]:[Amount]],operations[[Category]:[Category]],summary1[[#This Row],[Category]:[Category]],operations[[Month]:[Month]],summary1[[#Headers],[2]])} -> -765 | E8: {=SUMIFS(operations[[Amount]:[Amount]],operations[[Category]:[Category]],summary1[[#This Row],[Category]:[Category]],operations[[Month]:[Month]],summary1[[#Headers],[3]])} -> -300 | F8: {=SUMIFS(operations[[Amount]:[Amount]],operations[[Category]:[Category]],summary1[[#This Row],[Category]:[Category]],operations[[Month]:[Month]],summary1[[#Headers],[4]])} -> -100 | G8: {=SUMIFS(operations[[Amount]:[Amount]],operations[[Category]:[Category]],summary1[[#This Row],[Category]:[Category]],operations[[Month]:[Month]],summary1[[#Headers],[5]])} -> 0 | H8: {=SUMIFS(operations[[Amount]:[Amount]],operations[[Category]:[Category]],summary1[[#This Row],[Category]:[Category]],operations[[Month]:[Month]],summary1[[#Headers],[6]])} -> 0 | I8: {=SUMIFS(operations[[Amount]:[Amount]],operations[[Category]:[Category]],summary1[[#This Row],[Category]:[Category]],operations[[Month]:[Month]],summary1[[#Headers],[7]])} -> 0 | J8: {=SUMIFS(operations[[Amount]:[Amount]],operations[[Category]:[Category]],summary1[[#This Row],[Category]:[Category]],operations[[Month]:[Month]],summary1[[#Headers],[8]])} -> 0 | K8: {=SUMIFS(operations[[Amount]:[Amount]],operations[[Category]:[Category]],summary1[[#This Row],[Category]:[Category]],operations[[Month]:[Month]],summary1[[#Headers],[9]])} -> 0 | L8: {=SUMIFS(operations[[Amount]:[Amount]],operations[[Category]:[Category]],summary1[[#This Row],[Category]:[Category]],operations[[Month]:[Month]],summary1[[#Headers],[10]])} -> 0 | M8: {=SUMIFS(operations[[Amount]:[Amount]],operations[[Category]:[Category]],summary1[[#This Row],[Category]:[Category]],operations[[Month]:[Month]],summary1[[#Headers],[11]])} -> -234 | N8: {=SUMIFS(operations[[Amount]:[Amount]],operations[[Category]:[Category]],summary1[[#This Row],[Category]:[Category]],operations[[Month]:[Month]],summary1[[#Headers],[12]])} -> -700
A9: Studies | B9: Expense | C9: {=SUMIFS(operations[[Amount]:[Amount]],operations[[Category]:[Category]],summary1[[#This Row],[Category]:[Category]],operations[[Month]:[Month]],summary1[[#Headers],[1]])} -> -100 | D9: {=SUMIFS(operations[[Amount]:[Amount]],operations[[Category]:[Category]],summary1[[#This Row],[Category]:[Category]],operations[[Month]:[Month]],summary1[[#Headers],[2]])} -> -100 | E9: {=SUMIFS(operations[[Amount]:[Amount]],operations[[Category]:[Category]],summary1[[#This Row],[Category]:[Category]],operations[[Month]:[Month]],summary1[[#Headers],[3]])} -> -79.5 | F9: {=SUMIFS(operations[[Amount]:[Amount]],operations[[Category]:[Category]],summary1[[#This Row],[Category]:[Category]],operations[[Month]:[Month]],summary1[[#Headers],[4]])} -> -139 | G9: {=SUMIFS(operations[[Amount]:[Amount]],operations[[Category]:[Category]],summary1[[#This Row],[Category]:[Category]],operations[[Month]:[Month]],summary1[[#Headers],[5]])} -> 0 | H9: {=SUMIFS(operations[[Amount]:[Amount]],operations[[Category]:[Category]],summary1[[#This Row],[Category]:[Category]],operations[[Month]:[Month]],summary1[[#Headers],[6]])} -> 0 | I9: {=SUMIFS(operations[[Amount]:[Amount]],operations[[Category]:[Category]],summary1[[#This Row],[Category]:[Category]],operations[[Month]:[Month]],summary1[[#Headers],[7]])} -> 0 | J9: {=SUMIFS(operations[[Amount]:[Amount]],operations[[Category]:[Category]],summary1[[#This Row],[Category]:[Category]],operations[[Month]:[Month]],summary1[[#Headers],[8]])} -> 0 | K9: {=SUMIFS(operations[[Amount]:[Amount]],operations[[Category]:[Category]],summary1[[#This Row],[Category]:[Category]],operations[[Month]:[Month]],summary1[[#Headers],[9]])} -> 0 | L9: {=SUMIFS(operations[[Amount]:[Amount]],operations[[Category]:[Category]],summary1[[#This Row],[Category]:[Category]],operations[[Month]:[Month]],summary1[[#Headers],[10]])} -> 0 | M9: {=SUMIFS(operations[[Amount]:[Amount]],operations[[Category]:[Category]],summary1[[#This Row],[Category]:[Category]],operations[[Month]:[Month]],summary1[[#Headers],[11]])} -> 0 | N9: {=SUMIFS(operations[[Amount]:[Amount]],operations[[Category]:[Category]],summary1[[#This Row],[Category]:[Category]],operations[[Month]:[Month]],summary1[[#Headers],[12]])} -> -100
A10: Transportation | B10: Expense | C10: {=SUMIFS(operations[[Amount]:[Amount]],operations[[Category]:[Category]],summary1[[#This Row],[Category]:[Category]],operations[[Month]:[Month]],summary1[[#Headers],[1]])} -> -80 | D10: {=SUMIFS(operations[[Amount]:[Amount]],operations[[Category]:[Category]],summary1[[#This Row],[Category]:[Category]],operations[[Month]:[Month]],summary1[[#Headers],[2]])} -> -80 | E10: {=SUMIFS(operations[[Amount]:[Amount]],operations[[Category]:[Category]],summary1[[#This Row],[Category]:[Category]],operations[[Month]:[Month]],summary1[[#Headers],[3]])} -> -82.5 | F10: {=SUMIFS(operations[[Amount]:[Amount]],operations[[Category]:[Category]],summary1[[#This Row],[Category]:[Category]],operations[[Month]:[Month]],summary1[[#Headers],[4]])} -> -82.5 | G10: {=SUMIFS(operations[[Amount]:[Amount]],operations[[Category]:[Category]],summary1[[#This Row],[Category]:[Category]],operations[[Month]:[Month]],summary1[[#Headers],[5]])} -> -80 | H10: {=SUMIFS(operations[[Amount]:[Amount]],operations[[Category]:[Category]],summary1[[#This Row],[Category]:[Category]],operations[[Month]:[Month]],summary1[[#Headers],[6]])} -> -80 | I10: {=SUMIFS(operations[[Amount]:[Amount]],operations[[Category]:[Category]],summary1[[#This Row],[Category]:[Category]],operations[[Month]:[Month]],summary1[[#Headers],[7]])} -> -90 | J10: {=SUMIFS(operations[[Amount]:[Amount]],operations[[Category]:[Category]],summary1[[#This Row],[Category]:[Category]],operations[[Month]:[Month]],summary1[[#Headers],[8]])} -> -290 | K10: {=SUMIFS(operations[[Amount]:[Amount]],operations[[Category]:[Category]],summary1[[#This Row],[Category]:[Category]],operations[[Month]:[Month]],summary1[[#Headers],[9]])} -> -150 | L10: {=SUMIFS(operations[[Amount]:[Amount]],operations[[Category]:[Category]],summary1[[#This Row],[Category]:[Category]],operations[[Month]:[Month]],summary1[[#Headers],[10]])} -> -150 | M10: {=SUMIFS(operations[[Amount]:[Amount]],operations[[Category]:[Category]],summary1[[#This Row],[Category]:[Category]],operations[[Month]:[Month]],summary1[[#Headers],[11]])} -> -208 | N10: {=SUMIFS(operations[[Amount]:[Amount]],operations[[Category]:[Category]],summary1[[#This Row],[Category]:[Category]],operations[[Month]:[Month]],summary1[[#Headers],[12]])} -> 0
A11: Allowance | B11: Income | C11: {=SUMIFS(operations[[Amount]:[Amount]],operations[[Category]:[Category]],summary1[[#This Row],[Category]:[Category]],operations[[Month]:[Month]],summary1[[#Headers],[1]])} -> 250 | D11: {=SUMIFS(operations[[Amount]:[Amount]],operations[[Category]:[Category]],summary1[[#This Row],[Category]:[Category]],operations[[Month]:[Month]],summary1[[#Headers],[2]])} -> 0 | E11: {=SUMIFS(operations[[Amount]:[Amount]],operations[[Category]:[Category]],summary1[[#This Row],[Category]:[Category]],operations[[Month]:[Month]],summary1[[#Headers],[3]])} -> 0 | F11: {=SUMIFS(operations[[Amount]:[Amount]],operations[[Category]:[Category]],summary1[[#This Row],[Category]:[Category]],operations[[Month]:[Month]],summary1[[#Headers],[4]])} -> 0 | G11: {=SUMIFS(operations[[Amount]:[Amount]],operations[[Category]:[Category]],summary1[[#This Row],[Category]:[Category]],operations[[Month]:[Month]],summary1[[#Headers],[5]])} -> 0 | H11: {=SUMIFS(operations[[Amount]:[Amount]],operations[[Category]:[Category]],summary1[[#This Row],[Category]:[Category]],operations[[Month]:[Month]],summary1[[#Headers],[6]])} -> 400 | I11: {=SUMIFS(operations[[Amount]:[Amount]],operations[[Category]:[Category]],summary1[[#This Row],[Category]:[Category]],operations[[Month]:[Month]],summary1[[#Headers],[7]])} -> 0 | J11: {=SUMIFS(operations[[Amount]:[Amount]],operations[[Category]:[Category]],summary1[[#This Row],[Category]:[Category]],operations[[Month]:[Month]],summary1[[#Headers],[8]])} -> 0 | K11: {=SUMIFS(operations[[Amount]:[Amount]],operations[[Category]:[Category]],summary1[[#This Row],[Category]:[Category]],operations[[Month]:[Month]],summary1[[#Headers],[9]])} -> 0 | L11: {=SUMIFS(operations[[Amount]:[Amount]],operations[[Category]:[Category]],summary1[[#This Row],[Category]:[Category]],operations[[Month]:[Month]],summary1[[#Headers],[10]])} -> 0 | M11: {=SUMIFS(operations[[Amount]:[Amount]],operations[[Category]:[Category]],summary1[[#This Row],[Category]:[Category]],operations[[Month]:[Month]],summary1[[#Headers],[11]])} -> 0 | N11: {=SUMIFS(operations[[Amount]:[Amount]],operations[[Category]:[Category]],summary1[[#This Row],[Category]:[Category]],operations[[Month]:[Month]],summary1[[#Headers],[12]])} -> 0
A12: Financial | B12: Income | C12: {=SUMIFS(operations[[Amount]:[Amount]],operations[[Category]:[Category]],summary1[[#This Row],[Category]:[Category]],operations[[Month]:[Month]],summary1[[#Headers],[1]])} -> 105.5 | D12: {=SUMIFS(operations[[Amount]:[Amount]],operations[[Category]:[Category]],summary1[[#This Row],[Category]:[Category]],operations[[Month]:[Month]],summary1[[#Headers],[2]])} -> 115 | E12: {=SUMIFS(operations[[Amount]:[Amount]],operations[[Category]:[Category]],summary1[[#This Row],[Category]:[Category]],operations[[Month]:[Month]],summary1[[#Headers],[3]])} -> 150 | F12: {=SUMIFS(operations[[Amount]:[Amount]],operations[[Category]:[Category]],summary1[[#This Row],[Category]:[Category]],operations[[Month]:[Month]],summary1[[#Headers],[4]])} -> 150 | G12: {=SUMIFS(operations[[Amount]:[Amount]],operations[[Category]:[Category]],summary1[[#This Row],[Category]:[Category]],operations[[Month]:[Month]],summary1[[#Headers],[5]])} -> 0 | H12: {=SUMIFS(operations[[Amount]:[Amount]],operations[[Category]:[Category]],summary1[[#This Row],[Category]:[Category]],operations[[Month]:[Month]],summary1[[#Headers],[6]])} -> 0 | I12: {=SUMIFS(operations[[Amount]:[Amount]],operations[[Category]:[Category]],summary1[[#This Row],[Category]:[Category]],operations[[Month]:[Month]],summary1[[#Headers],[7]])} -> 120 | J12: {=SUMIFS(operations[[Amount]:[Amount]],operations[[Category]:[Category]],summary1[[#This Row],[Category]:[Category]],operations[[Month]:[Month]],summary1[[#Headers],[8]])} -> 0 | K12: {=SUMIFS(operations[[Amount]:[Amount]],operations[[Category]:[Category]],summary1[[#This Row],[Category]:[Category]],operations[[Month]:[Month]],summary1[[#Headers],[9]])} -> 0 | L12: {=SUMIFS(operations[[Amount]:[Amount]],operations[[Category]:[Category]],summary1[[#This Row],[Category]:[Category]],operations[[Month]:[Month]],summary1[[#Headers],[10]])} -> 0 | M12: {=SUMIFS(operations[[Amount]:[Amount]],operations[[Category]:[Category]],summary1[[#This Row],[Category]:[Category]],operations[[Month]:[Month]],summary1[[#Headers],[11]])} -> 0 | N12: {=SUMIFS(operations[[Amount]:[Amount]],operations[[Category]:[Category]],summary1[[#This Row],[Category]:[Category]],operations[[Month]:[Month]],summary1[[#Headers],[12]])} -> 0
A13: Gift | B13: Income | C13: {=SUMIFS(operations[[Amount]:[Amount]],operations[[Category]:[Category]],summary1[[#This Row],[Category]:[Category]],operations[[Month]:[Month]],summary1[[#Headers],[1]])} -> 0 | D13: {=SUMIFS(operations[[Amount]:[Amount]],operations[[Category]:[Category]],summary1[[#This Row],[Category]:[Category]],operations[[Month]:[Month]],summary1[[#Headers],[2]])} -> 0 | E13: {=SUMIFS(operations[[Amount]:[Amount]],operations[[Category]:[Category]],summary1[[#This Row],[Category]:[Category]],operations[[Month]:[Month]],summary1[[#Headers],[3]])} -> 5 | F13: {=SUMIFS(operations[[Amount]:[Amount]],operations[[Category]:[Category]],summary1[[#This Row],[Category]:[Category]],operations[[Month]:[Month]],summary1[[#Headers],[4]])} -> 50 | G13: {=SUMIFS(operations[[Amount]:[Amount]],operations[[Category]:[Category]],summary1[[#This Row],[Category]:[Category]],operations[[Month]:[Month]],summary1[[#Headers],[5]])} -> 0 | H13: {=SUMIFS(operations[[Amount]:[Amount]],operations[[Category]:[Category]],summary1[[#This Row],[Category]:[Category]],operations[[Month]:[Month]],summary1[[#Headers],[6]])} -> 0 | I13: {=SUMIFS(operations[[Amount]:[Amount]],operations[[Category]:[Category]],summary1[[#This Row],[Category]:[Category]],operations[[Month]:[Month]],summary1[[#Headers],[7]])} -> 800 | J13: {=SUMIFS(operations[[Amount]:[Amount]],operations[[Category]:[Category]],summary1[[#This Row],[Category]:[Category]],operations[[Month]:[Month]],summary1[[#Headers],[8]])} -> 400 | K13: {=SUMIFS(operations[[Amount]:[Amount]],operations[[Category]:[Category]],summary1[[#This Row],[Category]:[Category]],operations[[Month]:[Month]],summary1[[#Headers],[9]])} -> 0 | L13: {=SUMIFS(operations[[Amount]:[Amount]],operations[[Category]:[Category]],summary1[[#This Row],[Category]:[Category]],operations[[Month]:[Month]],summary1[[#Headers],[10]])} -> 0 | M13: {=SUMIFS(operations[[Amount]:[Amount]],operations[[Category]:[Category]],summary1[[#This Row],[Category]:[Category]],operations[[Month]:[Month]],summary1[[#Headers],[11]])} -> 400 | N13: {=SUMIFS(operations[[Amount]:[Amount]],operations[[Category]:[Category]],summary1[[#This Row],[Category]:[Category]],operations[[Month]:[Month]],summary1[[#Headers],[12]])} -> 2000
... A17: Transfer | B17: Transfer | C17: {=SUMIFS(operations[[Amount]:[Amount]],operations[[Category]:[Category]],summary1[[#This Row],[Category]:[Category]],operations[[Month]:[Month]],summary1[[#Headers],[1]])} -> 0 | D17: {=SUMIFS(operations[[Amount]:[Amount]],operations[[Category]:[Category]],summary1[[#This Row],[Category]:[Category]],operations[[Month]:[Month]],summary1[[#Headers],[2]])} -> 0 | E17: {=SUMIFS(operations[[Amount]:[Amount]],operations[[Category]:[Category]],summary1[[#This Row],[Category]:[Category]],operations[[Month]:[Month]],summary1[[#Headers],[3]])} -> 0 | F17: {=SUMIFS(operations[[Amount]:[Amount]],operations[[Category]:[Category]],summary1[[#This Row],[Category]:[Category]],operations[[Month]:[Month]],summary1[[#Headers],[4]])} -> 0 | G17: {=SUMIFS(operations[[Amount]:[Amount]],operations[[Category]:[Category]],summary1[[#This Row],[Category]:[Category]],operations[[Month]:[Month]],summary1[[#Headers],[5]])} -> 0 | H17: {=SUMIFS(operations[[Amount]:[Amount]],operations[[Category]:[Category]],summary1[[#This Row],[Category]:[Category]],operations[[Month]:[Month]],summary1[[#Headers],[6]])} -> 0 | I17: {=SUMIFS(operations[[Amount]:[Amount]],operations[[Category]:[Category]],summary1[[#This Row],[Category]:[Category]],operations[[Month]:[Month]],summary1[[#Headers],[7]])} -> 0 | J17: {=SUMIFS(operations[[Amount]:[Amount]],operations[[Category]:[Category]],summary1[[#This Row],[Category]:[Category]],operations[[Month]:[Month]],summary1[[#Headers],[8]])} -> -1020 | K17: {=SUMIFS(operations[[Amount]:[Amount]],operations[[Category]:[Category]],summary1[[#This Row],[Category]:[Category]],operations[[Month]:[Month]],summary1[[#Headers],[9]])} -> 0 | L17: {=SUMIFS(operations[[Amount]:[Amount]],operations[[Category]:[Category]],summary1[[#This Row],[Category]:[Category]],operations[[Month]:[Month]],summary1[[#Headers],[10]])} -> 0 | M17: {=SUMIFS(operations[[Amount]:[Amount]],operations[[Category]:[Category]],summary1[[#This Row],[Category]:[Category]],operations[[Month]:[Month]],summary1[[#Headers],[11]])} -> 0 | N17: {=SUMIFS(operations[[Amount]:[Amount]],operations[[Category]:[Category]],summary1[[#This Row],[Category]:[Category]],operations[[Month]:[Month]],summary1[[#Headers],[12]])} -> 0
A18: Total | C18: =SUBTOTAL(109,summary1[1]) -> 845.5 | D18: =SUBTOTAL(109,summary1[2]) -> 2464.5 | E18: =SUBTOTAL(109,summary1[3]) -> 755.61 | F18: =SUBTOTAL(109,summary1[4]) -> 726.84 | G18: =SUBTOTAL(109,summary1[5]) -> 1290 | H18: =SUBTOTAL(109,summary1[6]) -> 1170 | I18: =SUBTOTAL(109,summary1[7]) -> 2915 | J18: =SUBTOTAL(109,summary1[8]) -> 390.5 | K18: =SUBTOTAL(109,summary1[9]) -> 1751.5 | L18: =SUBTOTAL(109,summary1[10]) -> 1670 | M18: =SUBTOTAL(109,summary1[11]) -> 1400 | N18: =SUBTOTAL(109,summary1[12]) -> 2420

Sheet summary2
A1: Category | B1: Type | C1: 1 | D1: 2 | E1: 3 | F1: 4 | G1: 5 | H1: 6 | I1: 7 | J1: 8 | K1: 9 | L1: 10 | M1: 11 | N1: 12
A2: Accomodation | B2: Expense | C2: =SUMIFS(operations[[Amount]:[Amount]],operations[[Category]:[Category]],$A2,operations[[Month]:[Month]],C$1) -> -2000 | D2: =SUMIFS(operations[[Amount]:[Amount]],operations[[Category]:[Category]],$A2,operations[[Month]:[Month]],D$1) -> -2000 | E2: =SUMIFS(operations[[Amount]:[Amount]],operations[[Category]:[Category]],$A2,operations[[Month]:[Month]],E$1) -> -2000 | F2: =SUMIFS(operations[[Amount]:[Amount]],operations[[Category]:[Category]],$A2,operations[[Month]:[Month]],F$1) -> -2000 | G2: =SUMIFS(operations[[Amount]:[Amount]],operations[[Category]:[Category]],$A2,operations[[Month]:[Month]],G$1) -> -2000 | H2: =SUMIFS(operations[[Amount]:[Amount]],operations[[Category]:[Category]],$A2,operations[[Month]:[Month]],H$1) -> -2000 | I2: =SUMIFS(operations[[Amount]:[Amount]],operations[[Category]:[Category]],$A2,operations[[Month]:[Month]],I$1) -> -2000 | J2: =SUMIFS(operations[[Amount]:[Amount]],operations[[Category]:[Category]],$A2,operations[[Month]:[Month]],J$1) -> -2000 | ... N2: =SUMIFS(operations[[Amount]:[Amount]],operations[[Category]:[Category]],$A2,operations[[Month]:[Month]],N$1) -> -2000
A3: Clothing | B3: Expense | C3: =SUMIFS(operations[[Amount]:[Amount]],operations[[Category]:[Category]],$A3,operations[[Month]:[Month]],C$1) -> -80 | D3: =SUMIFS(operations[[Amount]:[Amount]],operations[[Category]:[Category]],$A3,operations[[Month]:[Month]],D$1) -> 0 | E3: =SUMIFS(operations[[Amount]:[Amount]],operations[[Category]:[Category]],$A3,operations[[Month]:[Month]],E$1) -> -469.9 | F3: =SUMIFS(operations[[Amount]:[Amount]],operations[[Category]:[Category]],$A3,operations[[Month]:[Month]],F$1) -> -149 | G3: =SUMIFS(operations[[Amount]:[Amount]],operations[[Category]:[Category]],$A3,operations[[Month]:[Month]],G$1) -> 0 | H3: =SUMIFS(operations[[Amount]:[Amount]],operations[[Category]:[Category]],$A3,operations[[Month]:[Month]],H$1) -> -300 | I3: =SUMIFS(operations[[Amount]:[Amount]],operations[[Category]:[Category]],$A3,operations[[Month]:[Month]],I$1) -> 250 | J3: =SUMIFS(operations[[Amount]:[Amount]],operations[[Category]:[Category]],$A3,operations[[Month]:[Month]],J$1) -> -300 | ... N3: =SUMIFS(operations[[Amount]:[Amount]],operations[[Category]:[Category]],$A3,operations[[Month]:[Month]],N$1) -> -120
A4: Entertainment | B4: Expense | C4: =SUMIFS(operations[[Amount]:[Amount]],operations[[Category]:[Category]],$A4,operations[[Month]:[Month]],C$1) -> -85 | D4: =SUMIFS(operations[[Amount]:[Amount]],operations[[Category]:[Category]],$A4,operations[[Month]:[Month]],D$1) -> -350 | E4: =SUMIFS(operations[[Amount]:[Amount]],operations[[Category]:[Category]],$A4,operations[[Month]:[Month]],E$1) -> -200 | F4: =SUMIFS(operations[[Amount]:[Amount]],operations[[Category]:[Category]],$A4,operations[[Month]:[Month]],F$1) -> -1057.9 | G4: =SUMIFS(operations[[Amount]:[Amount]],operations[[Category]:[Category]],$A4,operations[[Month]:[Month]],G$1) -> -80 | H4: =SUMIFS(operations[[Amount]:[Amount]],operations[[Category]:[Category]],$A4,operations[[Month]:[Month]],H$1) -> -200 | I4: =SUMIFS(operations[[Amount]:[Amount]],operations[[Category]:[Category]],$A4,operations[[Month]:[Month]],I$1) -> -700 | J4: =SUMIFS(operations[[Amount]:[Amount]],operations[[Category]:[Category]],$A4,operations[[Month]:[Month]],J$1) -> -250 | ... N4: =SUMIFS(operations[[Amount]:[Amount]],operations[[Category]:[Category]],$A4,operations[[Month]:[Month]],N$1) -> -450
A5: Groceries | B5: Expense | C5: =SUMIFS(operations[[Amount]:[Amount]],operations[[Category]:[Category]],$A5,operations[[Month]:[Month]],C$1) -> -1715 | D5: =SUMIFS(operations[[Amount]:[Amount]],operations[[Category]:[Category]],$A5,operations[[Month]:[Month]],D$1) -> -405.5 | E5: =SUMIFS(operations[[Amount]:[Amount]],operations[[Category]:[Category]],$A5,operations[[Month]:[Month]],E$1) -> -734.99 | F5: =SUMIFS(operations[[Amount]:[Amount]],operations[[Category]:[Category]],$A5,operations[[Month]:[Month]],F$1) -> -372.26 | G5: =SUMIFS(operations[[Amount]:[Amount]],operations[[Category]:[Category]],$A5,operations[[Month]:[Month]],G$1) -> -1000 | H5: =SUMIFS(operations[[Amount]:[Amount]],operations[[Category]:[Category]],$A5,operations[[Month]:[Month]],H$1) -> -1000 | I5: =SUMIFS(operations[[Amount]:[Amount]],operations[[Category]:[Category]],$A5,operations[[Month]:[Month]],I$1) -> -165 | J5: =SUMIFS(operations[[Amount]:[Amount]],operations[[Category]:[Category]],$A5,operations[[Month]:[Month]],J$1) -> -749.5 | ... N5: =SUMIFS(operations[[Amount]:[Amount]],operations[[Category]:[Category]],$A5,operations[[Month]:[Month]],N$1) -> -700
A6: Health&Beauty | B6: Expense | C6: =SUMIFS(operations[[Amount]:[Amount]],operations[[Category]:[Category]],$A6,operations[[Month]:[Month]],C$1) -> -100 | D6: =SUMIFS(operations[[Amount]:[Amount]],operations[[Category]:[Category]],$A6,operations[[Month]:[Month]],D$1) -> -250 | E6: =SUMIFS(operations[[Amount]:[Amount]],operations[[Category]:[Category]],$A6,operations[[Month]:[Month]],E$1) -> -9.5 | F6: =SUMIFS(operations[[Amount]:[Amount]],operations[[Category]:[Category]],$A6,operations[[Month]:[Month]],F$1) -> -23.5 | G6: =SUMIFS(operations[[Amount]:[Amount]],operations[[Category]:[Category]],$A6,operations[[Month]:[Month]],G$1) -> 0 | H6: =SUMIFS(operations[[Amount]:[Amount]],operations[[Category]:[Category]],$A6,operations[[Month]:[Month]],H$1) -> -100 | I6: =SUMIFS(operations[[Amount]:[Amount]],operations[[Category]:[Category]],$A6,operations[[Month]:[Month]],I$1) -> -300 | J6: =SUMIFS(operations[[Amount]:[Amount]],operations[[Category]:[Category]],$A6,operations[[Month]:[Month]],J$1) -> -400 | ... N6: =SUMIFS(operations[[Amount]:[Amount]],operations[[Category]:[Category]],$A6,operations[[Month]:[Month]],N$1) -> -10
A7: Multimedia | B7: Expense | C7: =SUMIFS(operations[[Amount]:[Amount]],operations[[Category]:[Category]],$A7,operations[[Month]:[Month]],C$1) -> -150 | D7: =SUMIFS(operations[[Amount]:[Amount]],operations[[Category]:[Category]],$A7,operations[[Month]:[Month]],D$1) -> -150 | E7: =SUMIFS(operations[[Amount]:[Amount]],operations[[Category]:[Category]],$A7,operations[[Month]:[Month]],E$1) -> -23 | F7: =SUMIFS(operations[[Amount]:[Amount]],operations[[Category]:[Category]],$A7,operations[[Month]:[Month]],F$1) -> -49 | G7: =SUMIFS(operations[[Amount]:[Amount]],operations[[Category]:[Category]],$A7,operations[[Month]:[Month]],G$1) -> -50 | H7: =SUMIFS(operations[[Amount]:[Amount]],operations[[Category]:[Category]],$A7,operations[[Month]:[Month]],H$1) -> -50 | I7: =SUMIFS(operations[[Amount]:[Amount]],operations[[Category]:[Category]],$A7,operations[[Month]:[Month]],I$1) -> 0 | J7: =SUMIFS(operations[[Amount]:[Amount]],operations[[Category]:[Category]],$A7,operations[[Month]:[Month]],J$1) -> 0 | ... N7: =SUMIFS(operations[[Amount]:[Amount]],operations[[Category]:[Category]],$A7,operations[[Month]:[Month]],N$1) -> 0
A8: Other expences | B8: Expense | C8: =SUMIFS(operations[[Amount]:[Amount]],operations[[Category]:[Category]],$A8,operations[[Month]:[Month]],C$1) -> -500 | D8: =SUMIFS(operations[[Amount]:[Amount]],operations[[Category]:[Category]],$A8,operations[[Month]:[Month]],D$1) -> -765 | E8: =SUMIFS(operations[[Amount]:[Amount]],operations[[Category]:[Category]],$A8,operations[[Month]:[Month]],E$1) -> -300 | F8: =SUMIFS(operations[[Amount]:[Amount]],operations[[Category]:[Category]],$A8,operations[[Month]:[Month]],F$1) -> -100 | G8: =SUMIFS(operations[[Amount]:[Amount]],operations[[Category]:[Category]],$A8,operations[[Month]:[Month]],G$1) -> 0 | H8: =SUMIFS(operations[[Amount]:[Amount]],operations[[Category]:[Category]],$A8,operations[[Month]:[Month]],H$1) -> 0 | I8: =SUMIFS(operations[[Amount]:[Amount]],operations[[Category]:[Category]],$A8,operations[[Month]:[Month]],I$1) -> 0 | J8: =SUMIFS(operations[[Amount]:[Amount]],operations[[Category]:[Category]],$A8,operations[[Month]:[Month]],J$1) -> 0 | ... N8: =SUMIFS(operations[[Amount]:[Amount]],operations[[Category]:[Category]],$A8,operations[[Month]:[Month]],N$1) -> -700
A9: Studies | B9: Expense | C9: =SUMIFS(operations[[Amount]:[Amount]],operations[[Category]:[Category]],$A9,operations[[Month]:[Month]],C$1) -> -100 | D9: =SUMIFS(operations[[Amount]:[Amount]],operations[[Category]:[Category]],$A9,operations[[Month]:[Month]],D$1) -> -100 | E9: =SUMIFS(operations[[Amount]:[Amount]],operations[[Category]:[Category]],$A9,operations[[Month]:[Month]],E$1) -> -79.5 | F9: =SUMIFS(operations[[Amount]:[Amount]],operations[[Category]:[Category]],$A9,operations[[Month]:[Month]],F$1) -> -139 | G9: =SUMIFS(operations[[Amount]:[Amount]],operations[[Category]:[Category]],$A9,operations[[Month]:[Month]],G$1) -> 0 | H9: =SUMIFS(operations[[Amount]:[Amount]],operations[[Category]:[Category]],$A9,operations[[Month]:[Month]],H$1) -> 0 | I9: =SUMIFS(operations[[Amount]:[Amount]],operations[[Category]:[Category]],$A9,operations[[Month]:[Month]],I$1) -> 0 | J9: =SUMIFS(operations[[Amount]:[Amount]],operations[[Category]:[Category]],$A9,operations[[Month]:[Month]],J$1) -> 0 | ... N9: =SUMIFS(operations[[Amount]:[Amount]],operations[[Category]:[Category]],$A9,operations[[Month]:[Month]],N$1) -> -100
A10: Transportation | B10: Expense | C10: =SUMIFS(operations[[Amount]:[Amount]],operations[[Category]:[Category]],$A10,operations[[Month]:[Month]],C$1) -> -80 | D10: =SUMIFS(operations[[Amount]:[Amount]],operations[[Category]:[Category]],$A10,operations[[Month]:[Month]],D$1) -> -80 | E10: =SUMIFS(operations[[Amount]:[Amount]],operations[[Category]:[Category]],$A10,operations[[Month]:[Month]],E$1) -> -82.5 | F10: =SUMIFS(operations[[Amount]:[Amount]],operations[[Category]:[Category]],$A10,operations[[Month]:[Month]],F$1) -> -82.5 | G10: =SUMIFS(operations[[Amount]:[Amount]],operations[[Category]:[Category]],$A10,operations[[Month]:[Month]],G$1) -> -80 | H10: =SUMIFS(operations[[Amount]:[Amount]],operations[[Category]:[Category]],$A10,operations[[Month]:[Month]],H$1) -> -80 | I10: =SUMIFS(operations[[Amount]:[Amount]],operations[[Category]:[Category]],$A10,operations[[Month]:[Month]],I$1) -> -90 | J10: =SUMIFS(operations[[Amount]:[Amount]],operations[[Category]:[Category]],$A10,operations[[Month]:[Month]],J$1) -> -290 | ... N10: =SUMIFS(operations[[Amount]:[Amount]],operations[[Category]:[Category]],$A10,operations[[Month]:[Month]],N$1) -> 0
B11: Expense Total | C11: =SUBTOTAL(9,C2:C10) -> -4810 | D11: =SUBTOTAL(9,D2:D10) -> -4100.5 | E11: =SUBTOTAL(9,E2:E10) -> -3899.39 | F11: =SUBTOTAL(9,F2:F10) -> -3973.16 | G11: =SUBTOTAL(9,G2:G10) -> -3210 | H11: =SUBTOTAL(9,H2:H10) -> -3730 | I11: =SUBTOTAL(9,I2:I10) -> -3005 | J11: =SUBTOTAL(9,J2:J10) -> -3989.5 | ... N11: =SUBTOTAL(9,N2:N10) -> -4080
A12: Allowance | B12: Income | C12: =SUMIFS(operations[[Amount]:[Amount]],operations[[Category]:[Category]],$A12,operations[[Month]:[Month]],C$1) -> 250 | D12: =SUMIFS(operations[[Amount]:[Amount]],operations[[Category]:[Category]],$A12,operations[[Month]:[Month]],D$1) -> 0 | E12: =SUMIFS(operations[[Amount]:[Amount]],operations[[Category]:[Category]],$A12,operations[[Month]:[Month]],E$1) -> 0 | F12: =SUMIFS(operations[[Amount]:[Amount]],operations[[Category]:[Category]],$A12,operations[[Month]:[Month]],F$1) -> 0 | G12: =SUMIFS(operations[[Amount]:[Amount]],operations[[Category]:[Category]],$A12,operations[[Month]:[Month]],G$1) -> 0 | H12: =SUMIFS(operations[[Amount]:[Amount]],operations[[Category]:[Category]],$A12,operations[[Month]:[Month]],H$1) -> 400 | I12: =SUMIFS(operations[[Amount]:[Amount]],operations[[Category]:[Category]],$A12,operations[[Month]:[Month]],I$1) -> 0 | J12: =SUMIFS(operations[[Amount]:[Amount]],operations[[Category]:[Category]],$A12,operations[[Month]:[Month]],J$1) -> 0 | ... N12: =SUMIFS(operations[[Amount]:[Amount]],operations[[Category]:[Category]],$A12,operations[[Month]:[Month]],N$1) -> 0
A13: Financial | B13: Income | C13: =SUMIFS(operations[[Amount]:[Amount]],operations[[Category]:[Category]],$A13,operations[[Month]:[Month]],C$1) -> 105.5 | D13: =SUMIFS(operations[[Amount]:[Amount]],operations[[Category]:[Category]],$A13,operations[[Month]:[Month]],D$1) -> 115 | E13: =SUMIFS(operations[[Amount]:[Amount]],operations[[Category]:[Category]],$A13,operations[[Month]:[Month]],E$1) -> 150 | F13: =SUMIFS(operations[[Amount]:[Amount]],operations[[Category]:[Category]],$A13,operations[[Month]:[Month]],F$1) -> 150 | G13: =SUMIFS(operations[[Amount]:[Amount]],operations[[Category]:[Category]],$A13,operations[[Month]:[Month]],G$1) -> 0 | H13: =SUMIFS(operations[[Amount]:[Amount]],operations[[Category]:[Category]],$A13,operations[[Month]:[Month]],H$1) -> 0 | I13: =SUMIFS(operations[[Amount]:[Amount]],operations[[Category]:[Category]],$A13,operations[[Month]:[Month]],I$1) -> 120 | J13: =SUMIFS(operations[[Amount]:[Amount]],operations[[Category]:[Category]],$A13,operations[[Month]:[Month]],J$1) -> 0 | ... N13: =SUMIFS(operations[[Amount]:[Amount]],operations[[Category]:[Category]],$A13,operations[[Month]:[Month]],N$1) -> 0
A14: Gift | B14: Income | C14: =SUMIFS(operations[[Amount]:[Amount]],operations[[Category]:[Category]],$A14,operations[[Month]:[Month]],C$1) -> 0 | D14: =SUMIFS(operations[[Amount]:[Amount]],operations[[Category]:[Category]],$A14,operations[[Month]:[Month]],D$1) -> 0 | E14: =SUMIFS(operations[[Amount]:[Amount]],operations[[Category]:[Category]],$A14,operations[[Month]:[Month]],E$1) -> 5 | F14: =SUMIFS(operations[[Amount]:[Amount]],operations[[Category]:[Category]],$A14,operations[[Month]:[Month]],F$1) -> 50 | G14: =SUMIFS(operations[[Amount]:[Amount]],operations[[Category]:[Category]],$A14,operations[[Month]:[Month]],G$1) -> 0 | H14: =SUMIFS(operations[[Amount]:[Amount]],operations[[Category]:[Category]],$A14,operations[[Month]:[Month]],H$1) -> 0 | I14: =SUMIFS(operations[[Amount]:[Amount]],operations[[Category]:[Category]],$A14,operations[[Month]:[Month]],I$1) -> 800 | J14: =SUMIFS(operations[[Amount]:[Amount]],operations[[Category]:[Category]],$A14,operations[[Month]:[Month]],J$1) -> 400 | ... N14: =SUMIFS(operations[[Amount]:[Amount]],operations[[Category]:[Category]],$A14,operations[[Month]:[Month]],N$1) -> 2000
A15: Other incoms | B15: Income | C15: =SUMIFS(operations[[Amount]:[Amount]],operations[[Category]:[Category]],$A15,operations[[Month]:[Month]],C$1) -> 800 | D15: =SUMIFS(operations[[Amount]:[Amount]],operations[[Category]:[Category]],$A15,operations[[Month]:[Month]],D$1) -> 1950 | E15: =SUMIFS(operations[[Amount]:[Amount]],operations[[Category]:[Category]],$A15,operations[[Month]:[Month]],E$1) -> 0 | F15: =SUMIFS(operations[[Amount]:[Amount]],operations[[Category]:[Category]],$A15,operations[[Month]:[Month]],F$1) -> 0 | G15: =SUMIFS(operations[[Amount]:[Amount]],operations[[Category]:[Category]],$A15,operations[[Month]:[Month]],G$1) -> 0 | H15: =SUMIFS(operations[[Amount]:[Amount]],operations[[Category]:[Category]],$A15,operations[[Month]:[Month]],H$1) -> 0 | I15: =SUMIFS(operations[[Amount]:[Amount]],operations[[Category]:[Category]],$A15,operations[[Month]:[Month]],I$1) -> 0 | J15: =SUMIFS(operations[[Amount]:[Amount]],operations[[Category]:[Category]],$A15,operations[[Month]:[Month]],J$1) -> 0 | ... N15: =SUMIFS(operations[[Amount]:[Amount]],operations[[Category]:[Category]],$A15,operations[[Month]:[Month]],N$1) -> 0
A16: Salary | B16: Income | C16: =SUMIFS(operations[[Amount]:[Amount]],operations[[Category]:[Category]],$A16,operations[[Month]:[Month]],C$1) -> 4500 | D16: =SUMIFS(operations[[Amount]:[Amount]],operations[[Category]:[Category]],$A16,operations[[Month]:[Month]],D$1) -> 4500 | E16: =SUMIFS(operations[[Amount]:[Amount]],operations[[Category]:[Category]],$A16,operations[[Month]:[Month]],E$1) -> 4500 | F16: =SUMIFS(operations[[Amount]:[Amount]],operations[[Category]:[Category]],$A16,operations[[Month]:[Month]],F$1) -> 4500 | G16: =SUMIFS(operations[[Amount]:[Amount]],operations[[Category]:[Category]],$A16,operations[[Month]:[Month]],G$1) -> 4500 | H16: =SUMIFS(operations[[Amount]:[Amount]],operations[[Category]:[Category]],$A16,operations[[Month]:[Month]],H$1) -> 4500 | I16: =SUMIFS(operations[[Amount]:[Amount]],operations[[Category]:[Category]],$A16,operations[[Month]:[Month]],I$1) -> 4500 | J16: =SUMIFS(operations[[Amount]:[Amount]],operations[[Category]:[Category]],$A16,operations[[Month]:[Month]],J$1) -> 4500 | ... N16: =SUMIFS(operations[[Amount]:[Amount]],operations[[Category]:[Category]],$A16,operations[[Month]:[Month]],N$1) -> 4500
A17: Scholarship | B17: Income | C17: =SUMIFS(operations[[Amount]:[Amount]],operations[[Category]:[Category]],$A17,operations[[Month]:[Month]],C$1) -> 0 | D17: =SUMIFS(operations[[Amount]:[Amount]],operations[[Category]:[Category]],$A17,operations[[Month]:[Month]],D$1) -> 0 | E17: =SUMIFS(operations[[Amount]:[Amount]],operations[[Category]:[Category]],$A17,operations[[Month]:[Month]],E$1) -> 0 | F17: =SUMIFS(operations[[Amount]:[Amount]],operations[[Category]:[Category]],$A17,operations[[Month]:[Month]],F$1) -> 0 | G17: =SUMIFS(operations[[Amount]:[Amount]],operations[[Category]:[Category]],$A17,operations[[Month]:[Month]],G$1) -> 0 | H17: =SUMIFS(operations[[Amount]:[Amount]],operations[[Category]:[Category]],$A17,operations[[Month]:[Month]],H$1) -> 0 | I17: =SUMIFS(operations[[Amount]:[Amount]],operations[[Category]:[Category]],$A17,operations[[Month]:[Month]],I$1) -> 500 | J17: =SUMIFS(operations[[Amount]:[Amount]],operations[[Category]:[Category]],$A17,operations[[Month]:[Month]],J$1) -> 500 | ... N17: =SUMIFS(operations[[Amount]:[Amount]],operations[[Category]:[Category]],$A17,operations[[Month]:[Month]],N$1) -> 0
B18: Income Total | C18: =SUBTOTAL(9,C12:C17) -> 5655.5 | D18: =SUBTOTAL(9,D12:D17) -> 6565 | E18: =SUBTOTAL(9,E12:E17) -> 4655 | F18: =SUBTOTAL(9,F12:F17) -> 4700 | G18: =SUBTOTAL(9,G12:G17) -> 4500 | H18: =SUBTOTAL(9,H12:H17) -> 4900 | I18: =SUBTOTAL(9,I12:I17) -> 5920 | J18: =SUBTOTAL(9,J12:J17) -> 5400 | ... N18: =SUBTOTAL(9,N12:N17) -> 6500
A19: Transfer | B19: Transfer | C19: =SUMIFS(operations[[Amount]:[Amount]],operations[[Category]:[Category]],$A19,operations[[Month]:[Month]],C$1) -> 0 | D19: =SUMIFS(operations[[Amount]:[Amount]],operations[[Category]:[Category]],$A19,operations[[Month]:[Month]],D$1) -> 0 | E19: =SUMIFS(operations[[Amount]:[Amount]],operations[[Category]:[Category]],$A19,operations[[Month]:[Month]],E$1) -> 0 | F19: =SUMIFS(operations[[Amount]:[Amount]],operations[[Category]:[Category]],$A19,operations[[Month]:[Month]],F$1) -> 0 | G19: =SUMIFS(operations[[Amount]:[Amount]],operations[[Category]:[Category]],$A19,operations[[Month]:[Month]],G$1) -> 0 | H19: =SUMIFS(operations[[Amount]:[Amount]],operations[[Category]:[Category]],$A19,operations[[Month]:[Month]],H$1) -> 0 | I19: =SUMIFS(operations[[Amount]:[Amount]],operations[[Category]:[Category]],$A19,operations[[Month]:[Month]],I$1) -> 0 | J19: =SUMIFS(operations[[Amount]:[Amount]],operations[[Category]:[Category]],$A19,operations[[Month]:[Month]],J$1) -> -1020 | ... N19: =SUMIFS(operations[[Amount]:[Amount]],operations[[Category]:[Category]],$A19,operations[[Month]:[Month]],N$1) -> 0
B20: Transfer Total | C20: =SUBTOTAL(9,C19:C19) -> 0 | D20: =SUBTOTAL(9,D19:D19) -> 0 | E20: =SUBTOTAL(9,E19:E19) -> 0 | F20: =SUBTOTAL(9,F19:F19) -> 0 | G20: =SUBTOTAL(9,G19:G19) -> 0 | H20: =SUBTOTAL(9,H19:H19) -> 0 | I20: =SUBTOTAL(9,I19:I19) -> 0 | J20: =SUBTOTAL(9,J19:J19) -> -1020 | ... N20: =SUBTOTAL(9,N19:N19) -> 0
B21: Grand Total | C21: =SUBTOTAL(9,C2:C19) -> 845.5 | D21: =SUBTOTAL(9,D2:D19) -> 2464.5 | E21: =SUBTOTAL(9,E2:E19) -> 755.61 | F21: =SUBTOTAL(9,F2:F19) -> 726.84 | G21: =SUBTOTAL(9,G2:G19) -> 1290 | H21: =SUBTOTAL(9,H2:H19) -> 1170 | I21: =SUBTOTAL(9,I2:I19) -> 2915 | J21: =SUBTOTAL(9,J2:J19) -> 390.5 | ... N21: =SUBTOTAL(9,N2:N19) -> 2420

Sheet summary3
A3: Sum of Amount | C3: Month
A4: Type | B4: Category | C4: 1 | D4: 2 | E4: 3 | F4: 4 | G4: 5 | H4: 6 | I4: 7 | J4: 8 | K4: 9 | L4: 10 | M4: 11 | N4: 12 | O4: Grand Total
A5: Expense | C5: -4810 | D5: -4100.5 | E5: -3899.39 | F5: -3973.16 | G5: -3210 | H5: -3730 | I5: -3005 | J5: -3989.5 | K5: -2748.5 | L5: -2830 | M5: -3500 | N5: -4080 | O5: -43876.05
A6: Income | C6: 5655.5 | D6: 6565 | E6: 4655 | F6: 4700 | G6: 4500 | H6: 4900 | I6: 5920 | J6: 5400 | K6: 4500 | L6: 4500 | M6: 4900 | N6: 6500 | O6: 62695.5
A7: Transfer | B7: Transfer | D7: 0 | F7: 0 | G7: 0 | H7: 0 | I7: 0 | J7: -1020 | K7: 0 | L7: 0 | M7: 0 | O7: -1020
A8: Transfer Total | D8: 0 | F8: 0 | G8: 0 | H8: 0 | I8: 0 | J8: -1020 | K8: 0 | L8: 0 | M8: 0 | O8: -1020
A9: Grand Total | C9: 845.5 | D9: 2464.5 | E9: 755.61 | F9: 726.84 | G9: 1290 | H9: 1170 | I9: 2915 | J9: 390.5 | K9: 1751.5 | L9: 1670 | M9: 1400 | N9: 2420 | O9: 17799.45
